Project1/controller.v
`timescale 1ns / 1ps

// `define reportval
`define testval

module controller(
	input clk,
	input reset,
	input start,
	output init,
	output running,
	output toggle,
	output finish,
	output wire bist_end
);

reg [3:0] state, next_state; 
parameter IDLE=0, START=1, INIT=2, RUNNING=3, FINISH=4;
`ifdef reportval
parameter NCLOCK = 650; //650 for group 2
`endif
`ifdef testval
parameter NCLOCK = 10;
`endif

reg [$clog2(NCLOCK):0] ncounter; //for some reason this doesent work for the report numbers
reg complete;
reg toggle_r;
reg reset_latch;

always @ (posedge clk) begin
	if(reset) begin
		state       <= IDLE;
	end
	else if(start & (state == IDLE) & !reset_latch) begin
		state       <= START;
	end
	else
		state       <= next_state;
end


always @(*) begin
	case (state)
		START:
			next_state = INIT;
		INIT:
			next_state = RUNNING;
		RUNNING:
			if(ncounter == NCLOCK)
				next_state = FINISH;
		FINISH:
			next_state = IDLE;	
		default:
			next_state  = IDLE;
	endcase
end

assign init     = (state == INIT);
assign running  = (state == RUNNING) & (ncounter < NCLOCK+1);
assign finish   = (state == FINISH); 
assign bist_end = (complete) & !(reset | start) ;
assign toggle   = (state == RUNNING) & toggle_r;

always @ (posedge clk) begin
	if(reset | (state == FINISH)) begin
		toggle_r <= 0;
		ncounter <= 0;
	end	
	else if(state == RUNNING) begin
		if(ncounter < NCLOCK) begin
			toggle_r <= !toggle_r;
		end
		else begin
			toggle_r <= 0;
		end
		ncounter <= ncounter + 1;
  	end
end

// always @ (negedge finish, posedge reset, posedge start) begin
// 	if(!finish & (state == END) & !reset)
// 		complete <= 1;
// end

always @ (negedge finish, posedge start, posedge reset) begin
	if(reset | start)
		complete = 0;
	else
		complete = 1;
	
end

always @ (posedge start) begin
	if(start & !(reset)) begin
		reset_latch <= 0;
	end
	else begin
		reset_latch <= 1;
	end

end

endmodule // controller

Project1/controller_tb.v

`timescale 1ns / 1ps

//===========SET TEST==========
`define normal
`define consequent_test
`define mid_start
`define start_reset
`define mid_reset

//  `define reportval
`define testval

module controller_tb;

    reg CLK;
    reg START;
    reg RESET;
    wire INIT, RUNNING, TOGGLE, FINISH, BIST_END;
    integer pulsecount = 0;
    integer runningcount = 0;

    parameter NCLOCK = 650; //650 for group 2

    controller uut(
        .clk(CLK),
        .reset(RESET),
        .start(START),
        .init(INIT),
        .running(RUNNING),
        .toggle(TOGGLE),
        .finish(FINISH),
        .bist_end(BIST_END)
    );                 
    
    initial
    begin
    	$dumpfile("dump.vcd");
        $dumpvars();
        
        CLK = 0;
    	START = 0;
    	RESET = 0;
    end

    always @ (posedge TOGGLE) begin
        pulsecount = pulsecount +1; 
    end

    always @ (posedge CLK) begin
        if(RUNNING)
            runningcount = runningcount + 1;
    end

    initial begin
        //first start

        `ifdef normal
        #13 RESET = 1;
        #13 RESET = 0;     
        #13 START = 1;
        #13 START = 0;
        `ifdef reportval
        #7000
        `endif
        `ifdef testval
        #125
        `endif
        $display("Number of pulses: %d",pulsecount);
        $display("Time of running: %d clock pulses",runningcount-1); //-1 because the first rising edge of the clock doesent count
        pulsecount = 0;
        runningcount = 0;
        //======Normal test========
        `endif
        
        
        //first start
        `ifdef consequent_test
        #13 RESET = 1;
        #13 RESET = 0;     
        #13 START = 1;
        #13 START = 0;
        `ifdef reportval
        #7000
        `endif
        `ifdef testval
        #125
        `endif
        //second normal start
        #13 START = 1;
        #13 START = 0;
        #120
        //======consequent running proof========
        `endif
        

        `ifdef mid_start
        #13 RESET = 1;
        #13 RESET = 0;     
        #13 START = 1;
        #13 START = 0;
        #30
        //second normal start
        #13 START = 1;
        #13 START = 0;
        `ifdef reportval
        #7000
        `endif
        `ifdef testval
        #125
        `endif
        //======mid start proof========
        `endif

        `ifdef start_reset
        #13 RESET = 1;
        #13 RESET = 0;     
        #13 START = 1;
        #13 START = 0;
        #115
        #13 RESET = 1;
        #13 START = 1;
        #13 RESET = 0;
        #13 START = 0;
        #13 START = 1;
        #13 START = 0; 
        `ifdef reportval
        #7000
        `endif
        `ifdef testval
        #125
        `endif
        //======start and reset HIGH test========
        `endif

        `ifdef mid_reset
        #13 RESET = 1;
        #13 RESET = 0;     
        #13 START = 1;
        #13 START = 0;
        #50
        RESET = 1;
        #13
        RESET = 0;
        #13
        //second normal start
        #13 START = 1;
        #13 START = 0;
        `ifdef reportval
        #7000
        `endif
        `ifdef testval
        #125
        `endif
        //======mid start proof========
        `endif

    #100 $finish;

    end

    always
        #5  CLK =  ! CLK;


    


endmodule

Project1/dump.vcd
$date
	Thu Apr  9 21:52:12 2020
$end
$version
	Icarus Verilog
$end
$timescale
	1ps
$end
$scope module controller_tb $end
$var wire 1 ! TOGGLE $end
$var wire 1 " RUNNING $end
$var wire 1 # INIT $end
$var wire 1 $ FINISH $end
$var wire 1 % BIST_END $end
$var reg 1 & CLK $end
$var reg 1 ' RESET $end
$var reg 1 ( START $end
$var integer 32 ) pulsecount [31:0] $end
$var integer 32 * runningcount [31:0] $end
$scope module uut $end
$var wire 1 % bist_end $end
$var wire 1 & clk $end
$var wire 1 ' reset $end
$var wire 1 " running $end
$var wire 1 ( start $end
$var wire 1 ! toggle $end
$var wire 1 # init $end
$var wire 1 $ finish $end
$var reg 1 + complete $end
$var reg 5 , ncounter [4:0] $end
$var reg 4 - next_state [3:0] $end
$var reg 1 . reset_latch $end
$var reg 4 / state [3:0] $end
$var reg 1 0 toggle_r $end
$upscope $end
$upscope $end
$enddefinitions $end
#0
$dumpvars
x0
bx /
x.
bx -
bx ,
x+
b0 *
b0 )
0(
0'
0&
x%
x$
x#
x"
x!
$end
#5000
1&
#10000
0&
#13000
0%
0+
1'
#15000
b0 -
0"
0!
b0 ,
00
0#
0$
b0 /
1&
#20000
0&
#25000
1&
#26000
0'
#30000
0&
#35000
1&
#39000
0.
1(
#40000
0&
#45000
b10 -
b1 /
1&
#50000
0&
#52000
0(
#55000
b11 -
1#
b10 /
1&
#60000
0&
#65000
1"
0#
b11 /
1&
#70000
0&
#75000
b1 )
1!
b1 ,
10
b1 *
1&
#80000
0&
#85000
0!
b10 ,
00
b10 *
1&
#90000
0&
#95000
b10 )
1!
b11 ,
10
b11 *
1&
#100000
0&
#105000
0!
b100 ,
00
b100 *
1&
#110000
0&
#115000
b11 )
1!
b101 ,
10
b101 *
1&
#120000
0&
#125000
0!
b110 ,
00
b110 *
1&
#130000
0&
#135000
b100 )
1!
b111 ,
10
b111 *
1&
#140000
0&
#145000
0!
b1000 ,
00
b1000 *
1&
#150000
0&
#155000
b101 )
1!
b1001 ,
10
b1001 *
1&
#160000
0&
#165000
b100 -
0!
b1010 ,
00
b1010 *
1&
#170000
0&
#175000
b0 -
0"
b1011 ,
1$
b100 /
b1011 *
1&
#177000
b0 *
b0 )
#180000
0&
#185000
1%
1+
0$
b0 /
b0 ,
1&
#190000
0%
0+
0&
1'
#195000
1&
#200000
0&
#203000
0'
#205000
1&
#210000
0&
#215000
1&
#216000
1(
#220000
0&
#225000
b10 -
b1 /
1&
#229000
0(
#230000
0&
#235000
b11 -
1#
b10 /
1&
#240000
0&
#245000
1"
0#
b11 /
1&
#250000
0&
#255000
b1 )
1!
b1 ,
10
b1 *
1&
#260000
0&
#265000
0!
b10 ,
00
b10 *
1&
#270000
0&
#275000
b10 )
1!
b11 ,
10
b11 *
1&
#280000
0&
#285000
0!
b100 ,
00
b100 *
1&
#290000
0&
#295000
b11 )
1!
b101 ,
10
b101 *
1&
#300000
0&
#305000
0!
b110 ,
00
b110 *
1&
#310000
0&
#315000
b100 )
1!
b111 ,
10
b111 *
1&
#320000
0&
#325000
0!
b1000 ,
00
b1000 *
1&
#330000
0&
#335000
b101 )
1!
b1001 ,
10
b1001 *
1&
#340000
0&
#345000
b100 -
0!
b1010 ,
00
b1010 *
1&
#350000
0&
#355000
b0 -
0"
b1011 ,
1$
b100 /
b1011 *
1&
#360000
0&
#365000
1%
1+
0$
b0 /
b0 ,
1&
#367000
0%
0+
1(
#370000
0&
#375000
b10 -
b1 /
1&
#380000
0&
0(
#385000
b11 -
1#
b10 /
1&
#390000
0&
#395000
1"
0#
b11 /
1&
#400000
0&
#405000
b110 )
1!
b1 ,
10
b1100 *
1&
#410000
0&
#415000
0!
b10 ,
00
b1101 *
1&
#420000
0&
#425000
b111 )
1!
b11 ,
10
b1110 *
1&
#430000
0&
#435000
0!
b100 ,
00
b1111 *
1&
#440000
0&
#445000
b1000 )
1!
b101 ,
10
b10000 *
1&
#450000
0&
#455000
0!
b110 ,
00
b10001 *
1&
#460000
0&
#465000
b1001 )
1!
b111 ,
10
b10010 *
1&
#470000
0&
#475000
0!
b1000 ,
00
b10011 *
1&
#480000
0&
#485000
b1010 )
1!
b1001 ,
10
b10100 *
1&
#490000
0&
#495000
b100 -
0!
b1010 ,
00
b10101 *
1&
#500000
0&
#505000
b0 -
0"
1$
b100 /
b1011 ,
b10110 *
1&
#510000
0&
#513000
1'
#515000
b0 ,
0$
b0 /
1&
#520000
0&
#525000
1&
#526000
0'
#530000
0&
#535000
1&
#539000
1(
#540000
0&
#545000
b10 -
b1 /
1&
#550000
0&
#552000
0(
#555000
b11 -
1#
b10 /
1&
#560000
0&
#565000
1"
0#
b11 /
1&
#570000
0&
#575000
b1011 )
1!
b1 ,
10
b10111 *
1&
#580000
0&
#585000
0!
b10 ,
00
b11000 *
1&
#590000
0&
#595000
b1100 )
1!
b11 ,
10
b11001 *
1&
1(
#600000
0&
#605000
0!
b100 ,
00
b11010 *
1&
#608000
0(
#610000
0&
#615000
b1101 )
1!
b101 ,
10
b11011 *
1&
#620000
0&
#625000
0!
b110 ,
00
b11100 *
1&
#630000
0&
#635000
b1110 )
1!
b111 ,
10
b11101 *
1&
#640000
0&
#645000
0!
b1000 ,
00
b11110 *
1&
#650000
0&
#655000
b1111 )
1!
b1001 ,
10
b11111 *
1&
#660000
0&
#665000
b100 -
0!
b1010 ,
00
b100000 *
1&
#670000
0&
#675000
b0 -
0"
b1011 ,
1$
b100 /
b100001 *
1&
#680000
0&
#685000
1%
1+
0$
b0 /
b0 ,
1&
#690000
0&
#695000
1&
#700000
0&
#705000
1&
#710000
0&
#715000
1&
#720000
0&
#725000
1&
#730000
0&
#735000
1&
#740000
0&
#745000
1&
#746000
0%
0+
1'
#750000
0&
#755000
1&
#759000
0'
#760000
0&
#765000
1&
#770000
0&
#772000
1(
#775000
b10 -
b1 /
1&
#780000
0&
#785000
b11 -
1#
b10 /
1&
0(
#790000
0&
#795000
1"
0#
b11 /
1&
#800000
0&
#805000
b10000 )
1!
b1 ,
10
b100010 *
1&
#810000
0&
#815000
0!
b10 ,
00
b100011 *
1&
#820000
0&
#825000
b10001 )
1!
b11 ,
10
b100100 *
1&
#830000
0&
#835000
0!
b100 ,
00
b100101 *
1&
#840000
0&
#845000
b10010 )
1!
b101 ,
10
b100110 *
1&
#850000
0&
#855000
0!
b110 ,
00
b100111 *
1&
#860000
0&
#865000
b10011 )
1!
b111 ,
10
b101000 *
1&
#870000
0&
#875000
0!
b1000 ,
00
b101001 *
1&
#880000
0&
#885000
b10100 )
1!
b1001 ,
10
b101010 *
1&
#890000
0&
#895000
b100 -
0!
b1010 ,
00
b101011 *
1&
#900000
0&
#905000
b0 -
0"
1$
b100 /
b1011 ,
b101100 *
1&
#910000
0&
#913000
1'
#915000
b0 ,
0$
b0 /
1&
#920000
0&
#925000
1&
#926000
1.
1(
#930000
0&
#935000
1&
#939000
0'
#940000
0&
#945000
1&
#950000
0&
#952000
0(
#955000
1&
#960000
0&
#965000
0.
1&
1(
#970000
0&
#975000
b10 -
b1 /
1&
#978000
0(
#980000
0&
#985000
b11 -
1#
b10 /
1&
#990000
0&
#995000
1"
0#
b11 /
1&
#1000000
0&
#1005000
b10101 )
1!
b1 ,
10
b101101 *
1&
#1010000
0&
#1015000
0!
b10 ,
00
b101110 *
1&
#1020000
0&
#1025000
b10110 )
1!
b11 ,
10
b101111 *
1&
#1030000
0&
#1035000
0!
b100 ,
00
b110000 *
1&
#1040000
0&
#1045000
b10111 )
1!
b101 ,
10
b110001 *
1&
#1050000
0&
#1055000
0!
b110 ,
00
b110010 *
1&
#1060000
0&
#1065000
b11000 )
1!
b111 ,
10
b110011 *
1&
#1070000
0&
#1075000
0!
b1000 ,
00
b110100 *
1&
#1080000
0&
#1085000
b11001 )
1!
b1001 ,
10
b110101 *
1&
#1090000
0&
#1095000
b100 -
0!
b1010 ,
00
b110110 *
1&
#1100000
0&
#1105000
b0 -
0"
1$
b100 /
b1011 ,
b110111 *
1&
#1110000
0&
#1115000
1%
1+
b0 ,
0$
b0 /
1&
#1116000
0%
0+
1'
#1120000
0&
#1125000
1&
#1129000
0'
#1130000
0&
#1135000
1&
#1140000
0&
#1142000
1(
#1145000
b10 -
b1 /
1&
#1150000
0&
#1155000
b11 -
1#
b10 /
1&
0(
#1160000
0&
#1165000
1"
0#
b11 /
1&
#1170000
0&
#1175000
b11010 )
1!
b1 ,
10
b111000 *
1&
#1180000
0&
#1185000
0!
b10 ,
00
b111001 *
1&
#1190000
0&
#1195000
b11011 )
1!
b11 ,
10
b111010 *
1&
#1200000
0&
#1205000
0"
b0 -
0!
b0 /
b0 ,
00
b111011 *
1&
1'
#1210000
0&
#1215000
1&
#1218000
0'
#1220000
0&
#1225000
1&
#1230000
0&
#1235000
1&
#1240000
0&
#1244000
1(
#1245000
b10 -
b1 /
1&
#1250000
0&
#1255000
b11 -
1#
b10 /
1&
#1257000
0(
#1260000
0&
#1265000
1"
0#
b11 /
1&
#1270000
0&
#1275000
b11100 )
1!
b1 ,
10
b111100 *
1&
#1280000
0&
#1285000
0!
b10 ,
00
b111101 *
1&
#1290000
0&
#1295000
b11101 )
1!
b11 ,
10
b111110 *
1&
#1300000
0&
#1305000
0!
b100 ,
00
b111111 *
1&
#1310000
0&
#1315000
b11110 )
1!
b101 ,
10
b1000000 *
1&
#1320000
0&
#1325000
0!
b110 ,
00
b1000001 *
1&
#1330000
0&
#1335000
b11111 )
1!
b111 ,
10
b1000010 *
1&
#1340000
0&
#1345000
0!
b1000 ,
00
b1000011 *
1&
#1350000
0&
#1355000
b100000 )
1!
b1001 ,
10
b1000100 *
1&
#1360000
0&
#1365000
b100 -
0!
b1010 ,
00
b1000101 *
1&
#1370000
0&
#1375000
b0 -
0"
b1011 ,
1$
b100 /
b1000110 *
1&
#1380000
0&
#1385000
1%
1+
0$
b0 /
b0 ,
1&
