Project1/controller.v

// `define NCLOCK 5

module controller(
    input clk,
    input reset,
    input start,
    output init,
    output running,
    output reg toggle,
    output finish,
    output wire bist_end
);

reg [3:0] state, next_state; 
reg [3:0] nclock;
parameter IDLE=0, START=1, INIT=2, RUNNING=3, FINISH=4, END=5;

reg [2:0] ncounter;
reg complete;

always @ (posedge clk, posedge start) begin
  if(clk) begin
    if(reset | bist_end) begin
        state       <= IDLE;
        toggle      <= 0;
        ncounter    <= 1;
        nclock      <= 5;
    end
    else if(start & !(reset) & (state == IDLE)) begin
        state       <= START;
        complete    <= 0;
    end
    else
        state       <= next_state;
    end
end


always @(*) begin
    case (state)
        START:
            next_state = INIT;
        INIT:
            next_state = RUNNING;
        RUNNING:
            if(ncounter == nclock)
                next_state = FINISH;
        FINISH:
            next_state = END;
        
        default:
            next_state  = IDLE;
    endcase
end

assign init     = (state == INIT);
assign running  = (state == RUNNING) & (ncounter < nclock+1);
assign finish   = (state == FINISH); 
assign bist_end = (complete) & !(reset | start) ;

always @ (posedge clk) begin
  if(state == RUNNING) begin
      if(ncounter < nclock-1) begin
        toggle = !toggle;
      end
      else begin
        toggle <= 0;
      end
      ncounter++;
  end
end

always @ (negedge finish, posedge reset, posedge start) begin
    if(!finish && state == END)
        complete <= 1;
    else if (reset) 
        complete <= 0;
    else if (start) 
        complete <= 0;
end

endmodule // controller

Project1/controller_tb.v

`timescale 1ns / 1ps

//===========SET TEST==========
// `define consequent_test
// `define mid_start
// `define start_reset
`define mid_reset

module controller_tb;

    reg CLK;
    reg START;
    reg RESET;
    wire INIT, RUNNING, TOGGLE, FINISH, BIST_END;

    controller uut(
        .clk(CLK),
        .reset(RESET),
        .start(START),
        .init(INIT),
        .running(RUNNING),
        .toggle(TOGGLE),
        .finish(FINISH),
        .bist_end(BIST_END)
    );                 
    
    initial
    begin
    	$dumpfile("dump.vcd");
        $dumpvars();
        
        CLK = 0;
    	START = 0;
    	RESET = 0;
    end           
    initial begin
        //first start
        `ifdef consequent_test
        #3 RESET = 1;
        #3 RESET = 0;     
        #3 START = 1;
        #3 START = 0;
        #100
        //second normal start
        #3 START = 1;
        #3 START = 0;
        //======consequent running proof========
        `endif
        

        `ifdef mid_start
        #3 RESET = 1;
        #3 RESET = 0;     
        #3 START = 1;
        #3 START = 0;
        #30
        //second normal start
        #3 START = 1;
        #3 START = 0;
        //======mid start proof========
        `endif

        `ifdef start_reset
        #3 RESET = 1;
        #3 RESET = 0;     
        #3 START = 1;
        #3 START = 0;
        #100
        #3 RESET = 1;
        #3 START = 1;
        #3 RESET = 0;
        #3 START = 0;
        #3 START = 1;
        #3 START = 0;
        //======start and reset HIGH test========
        `endif

        `ifdef mid_reset
        #3 RESET = 1;
        #3 RESET = 0;     
        #3 START = 1;
        #3 START = 0;
        #10
        RESET = 1;
        #3
        RESET = 0;
        #15
        //second normal start
        #3 START = 1;
        #3 START = 0;
        //======mid start proof========
        `endif

    end
    initial begin
        #300 $finish;
    end

    always 
    #5  CLK =  ! CLK;

endmodule

Project1/dump.vcd
$date
	Wed Apr  1 13:04:19 2020
$end
$version
	Icarus Verilog
$end
$timescale
	1ps
$end
$scope module controller_tb $end
$var wire 1 ! TOGGLE $end
$var wire 1 " RUNNING $end
$var wire 1 # INIT $end
$var wire 1 $ FINISH $end
$var wire 1 % BIST_END $end
$var reg 1 & CLK $end
$var reg 1 ' RESET $end
$var reg 1 ( START $end
$scope module uut $end
$var wire 1 % bist_end $end
$var wire 1 & clk $end
$var wire 1 ' reset $end
$var wire 1 " running $end
$var wire 1 ( start $end
$var wire 1 # init $end
$var wire 1 $ finish $end
$var reg 1 ) complete $end
$var reg 4 * nclock [3:0] $end
$var reg 3 + ncounter [2:0] $end
$var reg 4 , next_state [3:0] $end
$var reg 4 - state [3:0] $end
$var reg 1 ! toggle $end
$upscope $end
$upscope $end
$enddefinitions $end
#0
$dumpvars
bx -
bx ,
bx +
bx *
x)
0(
0'
0&
x%
x$
x#
x"
x!
$end
#3000
0)
0%
1'
#5000
b0 ,
0"
b101 *
b1 +
0!
0#
0$
b0 -
1&
#6000
0'
#9000
b10 ,
b1 -
1(
#10000
0&
#12000
0(
#15000
b11 ,
1#
b10 -
1&
#20000
0&
#22000
1'
#25000
1"
0#
b11 -
0'
1&
#30000
0&
#35000
b10 +
1!
1&
#40000
0&
#43000
1(
#45000
b11 +
0!
1&
#46000
0(
#50000
0&
#55000
b100 +
1!
1&
#60000
0&
#65000
0!
b100 ,
b101 +
1&
#70000
0&
#75000
b101 ,
1$
b100 -
0"
b110 +
1&
#80000
0&
#85000
1%
1)
b0 ,
0$
b101 -
1&
#90000
0&
#95000
b1 +
b0 -
1&
