Project1/controller.v

// `define NCLOCK 5

module controller(
    input clk,
    input reset,
    input start,
    output init,
    output running,
    output reg toggle,
    output finish,
    output reg bist_end
);

reg [3:0] state, next_state; 
reg [3:0] nclock;
parameter IDLE=0, INIT=1, RUNNING=2, FINISH=3, END=4;

reg [2:0] ncounter;

always @ (posedge clk) begin
  if(reset == 1) begin
    state   <= 0;
    toggle  <= 0;
    bist_end <= 0;
    ncounter <= 0;
    nclock <= 5;
  end
  else
    state <= next_state;
end


always @(*) begin
    case (state)
        IDLE:
            if(start)
                next_state = INIT;
        INIT:
            next_state = RUNNING;
        RUNNING:
            if(ncounter == nclock)
                next_state = FINISH;
        FINISH:
            next_state = IDLE;
        
        default:
            next_state  = IDLE;
    endcase
end

assign init = (state == INIT);
assign running = (state == RUNNING) && (ncounter < nclock);
assign finish = (state == FINISH); 
// assign bist_end = (state == END)

always @ (posedge clk) begin
  if(state == RUNNING) begin
      if(ncounter <= ncounter) begin
        toggle = !toggle;
        ncounter++;
      end
      else begin
          toggle <= 0;
      end
  end
end

always @ (negedge finish, posedge reset, posedge start) begin
    if(!finish)
        bist_end <= 1;
    else if (reset) 
        bist_end <= 0;
    else if (start) 
        bist_end <= 0;
end

endmodule // controller

Project1/controller_tb.v
`timescale 1ns / 1ps

module controller_tb;

    reg CLK;
    reg START;
    reg RESET;
    wire INIT, RUNNING, TOGGLE, FINISH, BIST_END;

    controller uut(
        .clk(CLK),
        .reset(RESET),
        .start(START),
        .init(INIT),
        .running(RUNNING),
        .toggle(TOGGLE),
        .finish(FINISH),
        .bist_end(BIST_END)
    );                 
    
    initial
    begin
    	$dumpfile("dump.vcd");
        $dumpvars();
        
        CLK = 0;
    	START = 0;
    	RESET = 0;
    end           
    initial begin
        #3 RESET = 1;
        #3 RESET = 0;     
    
        
        #3 START = 1;
        #3 START = 0;
    end
    initial begin
        #300 $finish;
    end

    always 
    #5  CLK =  ! CLK;

endmodule

Project1/dump.vcd
$date
	Tue Mar 31 18:20:07 2020
$end
$version
	Icarus Verilog
$end
$timescale
	1ps
$end
$scope module controller_tb $end
$var wire 1 ! TOGGLE $end
$var wire 1 " RUNNING $end
$var wire 1 # INIT $end
$var wire 1 $ FINISH $end
$var wire 1 % BIST_END $end
$var reg 1 & CLK $end
$var reg 1 ' RESET $end
$var reg 1 ( START $end
$scope module uut $end
$var wire 1 & clk $end
$var wire 1 ' reset $end
$var wire 1 " running $end
$var wire 1 ( start $end
$var wire 1 # init $end
$var wire 1 $ finish $end
$var reg 1 % bist_end $end
$var reg 4 ) nclock [3:0] $end
$var reg 3 * ncounter [2:0] $end
$var reg 4 + next_state [3:0] $end
$var reg 4 , state [3:0] $end
$var reg 1 ! toggle $end
$upscope $end
$upscope $end
$enddefinitions $end
#0
$dumpvars
bx ,
b0 +
bx *
bx )
0(
0'
0&
x%
x$
x#
x"
x!
$end
#3000
0%
1'
#5000
1%
0"
b101 )
b0 *
0!
0#
0$
b0 ,
1&
#6000
0'
#9000
b1 +
1(
#10000
0&
#12000
0(
#15000
b10 +
1#
b1 ,
1&
#20000
0&
#25000
1"
0#
b10 ,
1&
#30000
0&
#35000
b1 *
1!
1&
#40000
0&
#45000
b10 *
0!
1&
#50000
0&
#55000
b11 *
1!
1&
#60000
0&
#65000
b100 *
0!
1&
#70000
0&
#75000
b11 +
0"
b101 *
1!
1&
#80000
0&
#85000
b0 +
1$
b11 ,
b110 *
0!
1&
#90000
0&
#95000
0$
b0 ,
1&
