Project1/controller.v
`timescale 1ns / 1ps

module controller(
	input clk,
	input reset,
	input start,
	output init,
	output running,
	output toggle,
	output finish,
	output wire bist_end
);

reg [3:0] state, next_state; 
reg [3:0] nclock;
parameter IDLE=0, START=1, INIT=2, RUNNING=3, FINISH=4, END=5;
parameter NCLOCK = 10;

reg [$clog2(NCLOCK):0] ncounter;
reg complete;
reg toggle_r;
reg reset_latch;

always @ (posedge clk) begin
	if(reset) begin
		state       <= IDLE;
		nclock      <= NCLOCK;
		complete    <= 0;
	end
	else if(start & (state == IDLE) & !reset_latch) begin
		state       <= START;
		complete    <= 0;
	end
	else
		state       <= next_state;
end


always @(*) begin
	case (state)
		START:
			next_state = INIT;
		INIT:
			next_state = RUNNING;
		RUNNING:
			if(ncounter == nclock)
				next_state = FINISH;
		FINISH:
			next_state = END;
		END:
			if(bist_end)
				next_state = IDLE;	
		default:
			next_state  = IDLE;
	endcase
end

assign init     = (state == INIT);
assign running  = (state == RUNNING) & (ncounter < nclock+1);
assign finish   = (state == FINISH); 
assign bist_end = (complete) & !(reset | start) ;
assign toggle   = (state == RUNNING) & toggle_r;

always @ (posedge clk) begin
	if(reset | bist_end) begin
		toggle_r <= 0;
		ncounter <= 0;
	end	
	if(state == RUNNING) begin
		if(ncounter < nclock) begin
			toggle_r = !toggle_r;
		end
		else begin
			toggle_r <= 0;
		end
		ncounter <= ncounter + 1;
  	end
end

always @ (negedge finish, posedge reset, posedge start) begin
	if(!finish && state == END)
		complete <= 1;
end

always @ (posedge start) begin
	if(start & !(reset)) begin
		reset_latch <= 0;
	end
	else begin
		reset_latch <= 1;
	end

end

endmodule // controller

Project1/controller_tb.v

`timescale 1ns / 1ps

//===========SET TEST==========
`define consequent_test
`define mid_start
`define start_reset
`define mid_reset

module controller_tb;

    reg CLK;
    reg START;
    reg RESET;
    wire INIT, RUNNING, TOGGLE, FINISH, BIST_END;

    controller uut(
        .clk(CLK),
        .reset(RESET),
        .start(START),
        .init(INIT),
        .running(RUNNING),
        .toggle(TOGGLE),
        .finish(FINISH),
        .bist_end(BIST_END)
    );                 
    
    initial
    begin
    	$dumpfile("dump.vcd");
        $dumpvars();
        
        CLK = 0;
    	START = 0;
    	RESET = 0;
    end           
    initial begin
        //first start
        `ifdef consequent_test
        #13 RESET = 1;
        #13 RESET = 0;     
        #13 START = 1;
        #13 START = 0;
        #120
        //second normal start
        #13 START = 1;
        #13 START = 0;
        #120
        //======consequent running proof========
        `endif
        

        `ifdef mid_start
        #13 RESET = 1;
        #13 RESET = 0;     
        #13 START = 1;
        #13 START = 0;
        #30
        //second normal start
        #13 START = 1;
        #13 START = 0;
        #120
        //======mid start proof========
        `endif

        `ifdef start_reset
        #13 RESET = 1;
        #13 RESET = 0;     
        #13 START = 1;
        #13 START = 0;
        #100
        #13 RESET = 1;
        #13 START = 1;
        #13 RESET = 0;
        #13 START = 0;
        #13 START = 1;
        #13 START = 0; 
        # 120
        //======start and reset HIGH test========
        `endif

        `ifdef mid_reset
        #13 RESET = 1;
        #13 RESET = 0;     
        #13 START = 1;
        #13 START = 0;
        #10
        RESET = 1;
        #13
        RESET = 0;
        #13
        //second normal start
        #13 START = 1;
        #13 START = 0;
        #120
        //======mid start proof========
        `endif

    #100 $finish;

    end

    always 
    #5  CLK =  ! CLK;

endmodule

Project1/dump.vcd
$date
	Mon Apr  6 16:58:27 2020
$end
$version
	Icarus Verilog
$end
$timescale
	1ps
$end
$scope module controller_tb $end
$var wire 1 ! TOGGLE $end
$var wire 1 " RUNNING $end
$var wire 1 # INIT $end
$var wire 1 $ FINISH $end
$var wire 1 % BIST_END $end
$var reg 1 & CLK $end
$var reg 1 ' RESET $end
$var reg 1 ( START $end
$scope module uut $end
$var wire 1 % bist_end $end
$var wire 1 & clk $end
$var wire 1 ' reset $end
$var wire 1 " running $end
$var wire 1 ( start $end
$var wire 1 ! toggle $end
$var wire 1 # init $end
$var wire 1 $ finish $end
$var reg 1 ) complete $end
$var reg 4 * nclock [3:0] $end
$var reg 5 + ncounter [4:0] $end
$var reg 4 , next_state [3:0] $end
$var reg 1 - reset_latch $end
$var reg 4 . state [3:0] $end
$var reg 1 / toggle_r $end
$upscope $end
$upscope $end
$enddefinitions $end
#0
$dumpvars
x/
bx .
x-
bx ,
bx +
bx *
x)
0(
0'
0&
x%
x$
x#
x"
x!
$end
#5000
1&
#10000
0&
#13000
0)
b0 ,
0%
1'
#15000
0"
0!
b0 +
0/
b1010 *
0#
0$
b0 .
1&
#20000
0&
#25000
1&
#26000
0'
#30000
0&
#35000
1&
#39000
0-
1(
#40000
0&
#45000
b10 ,
b1 .
1&
#50000
0&
#52000
0(
#55000
b11 ,
1#
b10 .
1&
#60000
0&
#65000
1"
0#
b11 .
1&
#70000
0&
#75000
b1 +
1!
1/
1&
#80000
0&
#85000
b10 +
0!
0/
1&
#90000
0&
#95000
b11 +
1!
1/
1&
#100000
0&
#105000
b100 +
0!
0/
1&
#110000
0&
#115000
b101 +
1!
1/
1&
#120000
0&
#125000
b110 +
0!
0/
1&
#130000
0&
#135000
b111 +
1!
1/
1&
#140000
0&
#145000
b1000 +
0!
0/
1&
#150000
0&
#155000
b1001 +
1!
1/
1&
#160000
0&
#165000
b100 ,
b1010 +
0!
0/
1&
#170000
0&
#175000
b101 ,
0"
b1011 +
1$
b100 .
1&
#180000
0&
#185000
1)
0$
b101 .
1&
1(
#190000
0&
#195000
1&
#198000
b0 ,
1%
0(
#200000
0&
#205000
b0 .
b0 +
1&
#210000
0&
#215000
1&
#220000
0&
#225000
1&
#230000
0&
#235000
1&
#240000
0&
#245000
1&
#250000
0&
#255000
1&
#260000
0&
#265000
1&
#270000
0&
#275000
1&
#280000
0&
#285000
1&
#290000
0&
#295000
1&
#300000
0&
#305000
1&
#310000
0&
#315000
1&
#320000
0&
#325000
1&
#330000
0&
#331000
0)
0%
1'
#335000
1&
#340000
0&
#344000
0'
#345000
1&
#350000
0&
#355000
1&
#357000
1(
#360000
0&
#365000
b10 ,
b1 .
1&
#370000
0&
0(
#375000
b11 ,
1#
b10 .
1&
#380000
0&
#385000
1"
0#
b11 .
1&
#390000
0&
#395000
b1 +
1!
1/
1&
#400000
0&
#405000
b10 +
0!
0/
1&
#410000
0&
#413000
1(
#415000
b11 +
1!
1/
1&
#420000
0&
#425000
b100 +
0!
0/
1&
#426000
0(
#430000
0&
#435000
b101 +
1!
1/
1&
#440000
0&
#445000
b110 +
0!
0/
1&
#450000
0&
#455000
b111 +
1!
1/
1&
#460000
0&
#465000
b1000 +
0!
0/
1&
#470000
0&
#475000
b1001 +
1!
1/
1&
#480000
0&
#485000
b100 ,
b1010 +
0!
0/
1&
#490000
0&
#495000
b101 ,
0"
b1011 +
1$
b100 .
1&
#500000
0&
#505000
b0 ,
1%
1)
0$
b101 .
1&
#510000
0&
#515000
b0 +
b0 .
1&
#520000
0&
#525000
1&
#530000
0&
#535000
1&
#540000
0&
#545000
1&
#550000
0&
#555000
1&
#559000
0)
0%
1'
#560000
0&
#565000
1&
#570000
0&
#572000
0'
#575000
1&
#580000
0&
#585000
b10 ,
b1 .
1&
1(
#590000
0&
#595000
b11 ,
1#
b10 .
1&
#598000
0(
#600000
0&
#605000
1"
0#
b11 .
1&
#610000
0&
#615000
b1 +
1!
1/
1&
#620000
0&
#625000
b10 +
0!
0/
1&
#630000
0&
#635000
b11 +
1!
1/
1&
#640000
0&
#645000
b100 +
0!
0/
1&
#650000
0&
#655000
b101 +
1!
1/
1&
#660000
0&
#665000
b110 +
0!
0/
1&
#670000
0&
#675000
b111 +
1!
1/
1&
#680000
0&
#685000
b1000 +
0!
0/
1&
#690000
0&
#695000
b1001 +
1!
1/
1&
#700000
0&
#705000
b100 ,
b1010 +
0!
0/
1&
#710000
0&
#711000
1'
#715000
b0 ,
0"
b1011 +
b0 .
1&
#720000
0&
#724000
1-
1(
#725000
b0 +
1&
#730000
0&
#735000
1&
#737000
0'
#740000
0&
#745000
1&
#750000
0&
0(
#755000
1&
#760000
0&
#763000
0-
1(
#765000
b10 ,
b1 .
1&
#770000
0&
#775000
b11 ,
1#
b10 .
1&
#776000
0(
#780000
0&
#785000
1"
0#
b11 .
1&
#790000
0&
#795000
b1 +
1!
1/
1&
#800000
0&
#805000
b10 +
0!
0/
1&
#810000
0&
#815000
b11 +
1!
1/
1&
#820000
0&
#825000
b100 +
0!
0/
1&
#830000
0&
#835000
b101 +
1!
1/
1&
#840000
0&
#845000
b110 +
0!
0/
1&
#850000
0&
#855000
b111 +
1!
1/
1&
#860000
0&
#865000
b1000 +
0!
0/
1&
#870000
0&
#875000
b1001 +
1!
1/
1&
#880000
0&
#885000
b100 ,
b1010 +
0!
0/
1&
#890000
0&
#895000
b101 ,
0"
b1011 +
1$
b100 .
1&
#900000
0&
#905000
b0 ,
1%
1)
0$
b101 .
1&
#909000
0%
1'
#910000
0&
#915000
b0 +
0)
b0 .
1&
#920000
0&
#922000
0'
#925000
1&
#930000
0&
#935000
b10 ,
b1 .
1&
1(
#940000
0&
#945000
b11 ,
1#
b10 .
1&
#948000
0(
#950000
0&
#955000
1"
0#
b11 .
1&
#958000
1'
#960000
0&
#965000
0"
b0 ,
b0 .
b1 +
0!
0/
1&
#970000
0&
#971000
0'
#975000
1&
#980000
0&
#985000
1&
#990000
0&
#995000
1&
#997000
1(
#1000000
0&
#1005000
b10 ,
b1 .
1&
#1010000
0&
0(
#1015000
b11 ,
1#
b10 .
1&
#1020000
0&
#1025000
1"
0#
b11 .
1&
#1030000
0&
#1035000
b10 +
1!
1/
1&
#1040000
0&
#1045000
b11 +
0!
0/
1&
#1050000
0&
#1055000
b100 +
1!
1/
1&
#1060000
0&
#1065000
b101 +
0!
0/
1&
#1070000
0&
#1075000
b110 +
1!
1/
1&
#1080000
0&
#1085000
b111 +
0!
0/
1&
#1090000
0&
#1095000
b1000 +
1!
1/
1&
#1100000
0&
#1105000
b1001 +
0!
0/
1&
#1110000
0&
#1115000
b100 ,
b1010 +
1!
1/
1&
#1120000
0&
#1125000
b101 ,
0"
0!
1$
b100 .
b1011 +
0/
1&
#1130000
0&
#1135000
b0 ,
1%
1)
0$
b101 .
1&
#1140000
0&
#1145000
b0 .
b0 +
1&
