Project1/controller.v
`timescale 1ns / 1ps

module controller(
	input clk,
	input reset,
	input start,
	output init,
	output running,
	output toggle,
	output finish,
	output wire bist_end
);

reg [3:0] state, next_state; 
parameter IDLE=0, START=1, INIT=2, RUNNING=3, FINISH=4;
parameter NCLOCK = 10;

reg [$clog2(NCLOCK):0] ncounter;
reg complete;
reg toggle_r;
reg reset_latch;

always @ (posedge clk) begin
	if(reset) begin
		state       <= IDLE;
	end
	else if(start & (state == IDLE) & !reset_latch) begin
		state       <= START;
	end
	else
		state       <= next_state;
end


always @(*) begin
	case (state)
		START:
			next_state = INIT;
		INIT:
			next_state = RUNNING;
		RUNNING:
			if(ncounter == NCLOCK)
				next_state = FINISH;
		FINISH:
			next_state = IDLE;	
		default:
			next_state  = IDLE;
	endcase
end

assign init     = (state == INIT);
assign running  = (state == RUNNING) & (ncounter < NCLOCK+1);
assign finish   = (state == FINISH); 
assign bist_end = (complete) & !(reset | start) ;
assign toggle   = (state == RUNNING) & toggle_r;

always @ (posedge clk) begin
	if(reset | (state == FINISH)) begin
		toggle_r <= 0;
		ncounter <= 0;
	end	
	if(state == RUNNING) begin
		if(ncounter < NCLOCK) begin
			toggle_r <= !toggle_r;
		end
		else begin
			toggle_r <= 0;
		end
		ncounter <= ncounter + 1;
  	end
end

// always @ (negedge finish, posedge reset, posedge start) begin
// 	if(!finish & (state == END) & !reset)
// 		complete <= 1;
// end

always @ (negedge finish, posedge start, posedge reset) begin
	if(reset | start)
		complete = 0;
	else
		complete = 1;
	
end

always @ (posedge start) begin
	if(start & !(reset)) begin
		reset_latch <= 0;
	end
	else begin
		reset_latch <= 1;
	end

end

endmodule // controller

Project1/controller_tb.v

`timescale 1ns / 1ps

//===========SET TEST==========
`define consequent_test
`define mid_start
`define start_reset
`define mid_reset

module controller_tb;

    reg CLK;
    reg START;
    reg RESET;
    wire INIT, RUNNING, TOGGLE, FINISH, BIST_END;

    controller uut(
        .clk(CLK),
        .reset(RESET),
        .start(START),
        .init(INIT),
        .running(RUNNING),
        .toggle(TOGGLE),
        .finish(FINISH),
        .bist_end(BIST_END)
    );                 
    
    initial
    begin
    	$dumpfile("dump.vcd");
        $dumpvars();
        
        CLK = 0;
    	START = 0;
    	RESET = 0;
    end           
    initial begin
        //first start
        `ifdef consequent_test
        #13 RESET = 1;
        #13 RESET = 0;     
        #13 START = 1;
        #13 START = 0;
        #125
        //second normal start
        #13 START = 1;
        #13 START = 0;
        #120
        //======consequent running proof========
        `endif
        

        `ifdef mid_start
        #13 RESET = 1;
        #13 RESET = 0;     
        #13 START = 1;
        #13 START = 0;
        #30
        //second normal start
        #13 START = 1;
        #13 START = 0;
        #120
        //======mid start proof========
        `endif

        `ifdef start_reset
        #13 RESET = 1;
        #13 RESET = 0;     
        #13 START = 1;
        #13 START = 0;
        #115
        #13 RESET = 1;
        #13 START = 1;
        #13 RESET = 0;
        #13 START = 0;
        #13 START = 1;
        #13 START = 0; 
        # 120
        //======start and reset HIGH test========
        `endif

        `ifdef mid_reset
        #13 RESET = 1;
        #13 RESET = 0;     
        #13 START = 1;
        #13 START = 0;
        #50
        RESET = 1;
        #13
        RESET = 0;
        #13
        //second normal start
        #13 START = 1;
        #13 START = 0;
        #120
        //======mid start proof========
        `endif

    #100 $finish;

    end

    always (*)
    #5  CLK =  ! CLK;

endmodule

Project1/Vivado/Vivado.sim/sim_1/behav/xsim/dump.vcd
$date
   Thu Apr  9 02:07:07 2020
$end
$version
  2019.2
$end
$timescale
  1ps
$end
$scope module controller_tb $end
$var reg 1 ! CLK $end
$var reg 1 " START $end
$var reg 1 # RESET $end
$var wire 1 $ INIT $end
$var wire 1 % RUNNING $end
$var wire 1 & TOGGLE $end
$var wire 1 ' FINISH $end
$var wire 1 ( BIST_END $end
$scope module uut $end
$var wire 1 ) clk $end
$var wire 1 * reset $end
$var wire 1 + start $end
$var wire 1 $ init $end
$var wire 1 % running $end
$var wire 1 & toggle $end
$var wire 1 ' finish $end
$var wire 1 ( bist_end $end
$var reg 4 , state [3:0] $end
$var reg 4 - next_state [3:0] $end
$var reg 5 . ncounter [4:0] $end
$var reg 1 / complete $end
$var reg 1 0 toggle_r $end
$var reg 1 1 reset_latch $end
$var parameter 32 2 IDLE [31:0] $end
$var parameter 32 3 START [31:0] $end
$var parameter 32 4 INIT [31:0] $end
$var parameter 32 5 RUNNING [31:0] $end
$var parameter 32 6 FINISH [31:0] $end
$var parameter 32 7 NCLOCK [31:0] $end
$upscope $end
$upscope $end
$enddefinitions $end
#0
$dumpvars
0!
0"
0#
x$
x%
x&
x'
x(
0)
0*
0+
bx ,
bx -
bx .
x/
x0
x1
b0 2
b1 3
b10 4
b11 5
b100 6
b1010 7
$end
#5000
1!
1)
bx ,
#10000
0!
0)
#13000
1#
0(
1*
0/
#15000
1!
0$
0%
0&
0'
1)
b0 ,
b0 -
b0 .
00
#20000
0!
0)
#25000
1!
1)
b0 ,
b0 .
00
#26000
0#
0(
0*
#30000
0!
0)
#35000
1!
1)
b0 ,
#39000
1"
0(
1+
01
#40000
0!
0)
#45000
1!
0$
0%
0&
0'
1)
b1 ,
b10 -
#50000
0!
0)
#52000
0"
0(
0+
#55000
1!
1$
0%
0&
0'
1)
b10 ,
b11 -
#60000
0!
0)
#65000
1!
0$
1%
0&
0'
1)
b11 ,
#70000
0!
0)
#75000
1!
1%
1&
1)
b11 ,
b1 .
10
#80000
0!
0)
#85000
1!
1%
0&
1)
b11 ,
b10 .
00
#90000
0!
0)
#95000
1!
1%
1&
1)
b11 ,
b11 .
10
#100000
0!
0)
#105000
1!
1%
0&
1)
b11 ,
b100 .
00
#110000
0!
0)
#115000
1!
1%
1&
1)
b11 ,
b101 .
10
#120000
0!
0)
#125000
1!
1%
0&
1)
b11 ,
b110 .
00
#130000
0!
0)
#135000
1!
1%
1&
1)
b11 ,
b111 .
10
#140000
0!
0)
#145000
1!
1%
0&
1)
b11 ,
b1000 .
00
#150000
0!
0)
#155000
1!
1%
1&
1)
b11 ,
b1001 .
10
#160000
0!
0)
#165000
1!
1%
0&
1)
b11 ,
b100 -
b1010 .
00
#170000
0!
0)
#175000
1!
0$
0%
0&
1'
1)
b100 ,
b0 -
b1011 .
00
#180000
0!
0)
#185000
1!
0$
0%
0&
0'
1(
1)
b0 ,
b0 -
b0 .
1/
00
#190000
0!
1"
0(
0)
1+
0/
01
#195000
1!
0$
0%
0&
0'
1)
b1 ,
b10 -
#200000
0!
0)
#203000
0"
0(
0+
#205000
1!
1$
0%
0&
0'
1)
b10 ,
b11 -
#210000
0!
0)
#215000
1!
0$
1%
0&
0'
1)
b11 ,
#220000
0!
0)
#225000
1!
1%
1&
1)
b11 ,
b1 .
10
#230000
0!
0)
#235000
1!
1%
0&
1)
b11 ,
b10 .
00
#240000
0!
0)
#245000
1!
1%
1&
1)
b11 ,
b11 .
10
#250000
0!
0)
#255000
1!
1%
0&
1)
b11 ,
b100 .
00
#260000
0!
0)
#265000
1!
1%
1&
1)
b11 ,
b101 .
10
#270000
0!
0)
#275000
1!
1%
0&
1)
b11 ,
b110 .
00
#280000
0!
0)
#285000
1!
1%
1&
1)
b11 ,
b111 .
10
#290000
0!
0)
#295000
1!
1%
0&
1)
b11 ,
b1000 .
00
#300000
0!
0)
#305000
1!
1%
1&
1)
b11 ,
b1001 .
10
#310000
0!
0)
#315000
1!
1%
0&
1)
b11 ,
b100 -
b1010 .
00
#320000
0!
0)
#325000
1!
0$
0%
0&
1'
1)
b100 ,
b0 -
b1011 .
00
#330000
0!
0)
#335000
1!
0$
0%
0&
0'
1(
1)
b0 ,
b0 -
b0 .
1/
00
#336000
1#
0(
1*
0/
#340000
0!
0)
#345000
1!
1)
b0 ,
b0 .
00
#349000
0#
0(
0*
#350000
0!
0)
#355000
1!
1)
b0 ,
#360000
0!
0)
#362000
1"
0(
1+
01
#365000
1!
0$
0%
0&
0'
1)
b1 ,
b10 -
#370000
0!
0)
#375000
1!
0"
1$
0%
0&
0'
0(
1)
0+
b10 ,
b11 -
#380000
0!
0)
#385000
1!
0$
1%
0&
0'
1)
b11 ,
#390000
0!
0)
#395000
1!
1%
1&
1)
b11 ,
b1 .
10
#400000
0!
0)
#405000
1!
1%
0&
1)
b11 ,
b10 .
00
#410000
0!
0)
#415000
1!
1%
1&
1)
b11 ,
b11 .
10
#418000
1"
0(
1+
01
#420000
0!
0)
#425000
1!
1%
0&
1)
b11 ,
b100 .
00
#430000
0!
0)
#431000
0"
0(
0+
#435000
1!
1%
1&
1)
b11 ,
b101 .
10
#440000
0!
0)
#445000
1!
1%
0&
1)
b11 ,
b110 .
00
#450000
0!
0)
#455000
1!
1%
1&
1)
b11 ,
b111 .
10
#460000
0!
0)
#465000
1!
1%
0&
1)
b11 ,
b1000 .
00
#470000
0!
0)
#475000
1!
1%
1&
1)
b11 ,
b1001 .
10
#480000
0!
0)
#485000
1!
1%
0&
1)
b11 ,
b100 -
b1010 .
00
#490000
0!
0)
#495000
1!
0$
0%
0&
1'
1)
b100 ,
b0 -
b1011 .
00
#500000
0!
0)
#505000
1!
0$
0%
0&
0'
1(
1)
b0 ,
b0 -
b0 .
1/
00
#510000
0!
0)
#515000
1!
1)
b0 ,
#520000
0!
0)
#525000
1!
1)
b0 ,
#530000
0!
0)
#535000
1!
1)
b0 ,
#540000
0!
0)
#545000
1!
1)
b0 ,
#550000
0!
0)
#555000
1!
1)
b0 ,
#560000
0!
0)
#564000
1#
0(
1*
0/
#565000
1!
1)
b0 ,
b0 .
00
#570000
0!
0)
#575000
1!
1)
b0 ,
b0 .
00
#577000
0#
0(
0*
#580000
0!
0)
#585000
1!
1)
b0 ,
#590000
0!
1"
0(
0)
1+
01
#595000
1!
0$
0%
0&
0'
1)
b1 ,
b10 -
#600000
0!
0)
#603000
0"
0(
0+
#605000
1!
1$
0%
0&
0'
1)
b10 ,
b11 -
#610000
0!
0)
#615000
1!
0$
1%
0&
0'
1)
b11 ,
#620000
0!
0)
#625000
1!
1%
1&
1)
b11 ,
b1 .
10
#630000
0!
0)
#635000
1!
1%
0&
1)
b11 ,
b10 .
00
#640000
0!
0)
#645000
1!
1%
1&
1)
b11 ,
b11 .
10
#650000
0!
0)
#655000
1!
1%
0&
1)
b11 ,
b100 .
00
#660000
0!
0)
#665000
1!
1%
1&
1)
b11 ,
b101 .
10
#670000
0!
0)
#675000
1!
1%
0&
1)
b11 ,
b110 .
00
#680000
0!
0)
#685000
1!
1%
1&
1)
b11 ,
b111 .
10
#690000
0!
0)
#695000
1!
1%
0&
1)
b11 ,
b1000 .
00
#700000
0!
0)
#705000
1!
1%
1&
1)
b11 ,
b1001 .
10
#710000
0!
0)
#715000
1!
1%
0&
1)
b11 ,
b100 -
b1010 .
00
#720000
0!
0)
#725000
1!
0$
0%
0&
1'
1)
b100 ,
b0 -
b1011 .
00
#730000
0!
0)
#731000
1#
0(
1*
#735000
1!
0$
0%
0&
0'
1)
b0 ,
b0 -
b0 .
00
#740000
0!
0)
#744000
1"
0(
1+
11
#745000
1!
1)
b0 ,
b0 .
00
#750000
0!
0)
#755000
1!
1)
b0 ,
b0 .
00
#757000
0#
0(
0*
#760000
0!
0)
#765000
1!
1)
b0 ,
#770000
0!
0"
0(
0)
0+
#775000
1!
1)
b0 ,
#780000
0!
0)
#783000
1"
0(
1+
01
#785000
1!
0$
0%
0&
0'
1)
b1 ,
b10 -
#790000
0!
0)
#795000
1!
1$
0%
0&
0'
1)
b10 ,
b11 -
#796000
0"
0(
0+
#800000
0!
0)
#805000
1!
0$
1%
0&
0'
1)
b11 ,
#810000
0!
0)
#815000
1!
1%
1&
1)
b11 ,
b1 .
10
#820000
0!
0)
#825000
1!
1%
0&
1)
b11 ,
b10 .
00
#830000
0!
0)
#835000
1!
1%
1&
1)
b11 ,
b11 .
10
#840000
0!
0)
#845000
1!
1%
0&
1)
b11 ,
b100 .
00
#850000
0!
0)
#855000
1!
1%
1&
1)
b11 ,
b101 .
10
#860000
0!
0)
#865000
1!
1%
0&
1)
b11 ,
b110 .
00
#870000
0!
0)
#875000
1!
1%
1&
1)
b11 ,
b111 .
10
#880000
0!
0)
#885000
1!
1%
0&
1)
b11 ,
b1000 .
00
#890000
0!
0)
#895000
1!
1%
1&
1)
b11 ,
b1001 .
10
#900000
0!
0)
#905000
1!
1%
0&
1)
b11 ,
b100 -
b1010 .
00
#910000
0!
0)
#915000
1!
0$
0%
0&
1'
1)
b100 ,
b0 -
b1011 .
00
#920000
0!
0)
#925000
1!
0$
0%
0&
0'
1(
1)
b0 ,
b0 -
b0 .
1/
00
#929000
1#
0(
1*
0/
#930000
0!
0)
#935000
1!
1)
b0 ,
b0 .
00
#940000
0!
0)
#942000
0#
0(
0*
#945000
1!
1)
b0 ,
#950000
0!
0)
#955000
1!
1"
0$
0%
0&
0'
0(
1)
1+
b1 ,
b10 -
01
#960000
0!
0)
#965000
1!
1$
0%
0&
0'
1)
b10 ,
b11 -
#968000
0"
0(
0+
#970000
0!
0)
#975000
1!
0$
1%
0&
0'
1)
b11 ,
#980000
0!
0)
#985000
1!
1%
1&
1)
b11 ,
b1 .
10
#990000
0!
0)
#995000
1!
1%
0&
1)
b11 ,
b10 .
00
