Project2/controller.v
`timescale 1ns / 1ps

`define reportval
//`define testval

module controller(
	input clk,
	input reset,
	input start,
	output init,
	output toggle,
	output running,
	output finish,
	output bist_end,
	output pass_fail
);

reg [2:0] state, next_state; 
parameter IDLE=0, START=1, INIT=2, RUNNING=3, FINISH=4;
`ifdef reportval
parameter NCLOCK = 650; //650 for group 2
`endif
`ifdef testval
parameter NCLOCK = 10; //this needs to be commented in order to generate code coverage. Xcellium does not recognize define parameters
`endif

reg [$clog2(NCLOCK):0] ncounter;
reg complete;
reg toggle_r;
reg reset_latch;

always @ (posedge clk) begin
	if(reset) begin
		state       <= IDLE;
	end
	else if(start & (state == IDLE) & !reset_latch) begin
		state       <= START;
	end
	else
		state       <= next_state;
end


always @(*) begin
	case (state)
		START:
			next_state = INIT;
		INIT:
			next_state = RUNNING;
		RUNNING:
			if(ncounter == NCLOCK)
				next_state = FINISH;
			else
				next_state = RUNNING;
		FINISH:
			next_state = IDLE;	
		default:
			next_state  = IDLE;
	endcase
end

assign init     = (state == INIT);
assign running  = (state == RUNNING) & (ncounter < NCLOCK);
assign finish   = (state == FINISH); 
assign bist_end = (complete) & !(reset | start) ;
assign toggle   = (state == RUNNING) & toggle_r;

always @ (posedge clk) begin
	if(reset | (state == FINISH)) begin
		toggle_r <= 0;
		ncounter <= 0;
	end	
	else if(state == RUNNING) begin
		if(ncounter < NCLOCK-1) begin
			toggle_r <= !toggle_r;
		end
		else begin
			toggle_r <= 0;
		end
		ncounter <= ncounter + 1;
  	end
end

wire complete_c;
assign complete_c = reset | start;

always @ (negedge finish) begin
	if(complete_c)
		complete <= 0;
	else
		complete <= 1;
	
end

wire latch_c;
assign latch_c = start ^ (reset);

always @ (posedge start) begin
	if(latch_c) begin
		reset_latch <= 1;
	end
	else begin
		reset_latch <= 0;
	end

end

endmodule // controller

Project2/controller_tb.v

`timescale 1ns / 1ps

//===========SET TEST==========
`define normal
// `define consequent_test
// `define mid_start
// `define start_reset
// `define mid_reset

//==========SET NCLOCK========
`define reportval
//`define testval

module controller_tb;

    reg CLK;
    reg START;
    reg RESET;
    wire INIT, RUNNING, TOGGLE, FINISH, BIST_END;
    integer pulsecount = 0;
    integer runningcount = 0;

    parameter NCLOCK = 650; //650 for group 2

    controller uut(
        .clk(CLK),
        .reset(RESET),
        .start(START),
        .init(INIT),
        .running(RUNNING),
        .toggle(TOGGLE),
        .finish(FINISH),
        .bist_end(BIST_END)
    );                 
    
    initial
    begin
    	$dumpfile("controller_test.vcd");
        $dumpvars();
        
        CLK = 0;
    	START = 0;
    	RESET = 0;
    end

    always @ (posedge TOGGLE) begin
        pulsecount = pulsecount +1; 
    end

    always @ (posedge CLK) begin
        if(RUNNING)
            runningcount = runningcount + 1;
    end

    initial begin
        //first start

        `ifdef normal
        wait(!CLK);
        #1 RESET = 1;
        #5 RESET = 0;   
        wait(!CLK);  
        #1 START = 1;
        #5 START = 0;
        `ifdef reportval
        #7000
        `endif
        `ifdef testval
        #125
        `endif
        $display("Number of pulses: %d pulses." ,pulsecount);
        $display("Time of running: %d clock pulses",runningcount-1); //-1 because the first rising edge of the clock doesent count
        pulsecount = 0;
        runningcount = 0;
        //======Normal test========
        `endif
        
        
        //first start
        `ifdef consequent_test
        #13 RESET = 1;
        #13 RESET = 0;     
        #13 START = 1;
        #13 START = 0;
        `ifdef reportval
        #7000
        `endif
        `ifdef testval
        #125
        `endif
        //second normal start
        #13 START = 1;
        #13 START = 0;
        #120
        //======consequent running proof========
        `endif
        

        `ifdef mid_start
        #13 RESET = 1;
        #13 RESET = 0;     
        #13 START = 1;
        #13 START = 0;
        #30
        //second normal start
        #13 START = 1;
        #13 START = 0;
        `ifdef reportval
        #7000
        `endif
        `ifdef testval
        #125
        `endif
        //======mid start proof========
        `endif

        `ifdef start_reset
        #13 RESET = 1;
        #13 RESET = 0;     
        #13 START = 1;
        #13 START = 0;
        #115
        #13 RESET = 1;
        #13 START = 1;
        #13 RESET = 0;
        #13 START = 0;
        #13 START = 1;
        #13 START = 0; 
        `ifdef reportval
        #7000
        `endif
        `ifdef testval
        #125
        `endif
        //======start and reset HIGH test========
        `endif

        `ifdef mid_reset
        #13 RESET = 1;
        #13 RESET = 0;     
        #13 START = 1;
        #13 START = 0;
        #50
        RESET = 1;
        #13
        RESET = 0;
        #13
        //second normal start
        #13 START = 1;
        #13 START = 0;
        `ifdef reportval
        #7000
        `endif
        `ifdef testval
        #125
        `endif
        //======mid start proof========
        `endif

    #100 $finish;

    end

    always
        #5  CLK =  ! CLK;


    


endmodule

Project2/controller_test.vcd
$date
	Sun May 17 22:39:38 2020
$end
$version
	Icarus Verilog
$end
$timescale
	1ps
$end
$scope module controller_tb $end
$var wire 1 ! TOGGLE $end
$var wire 1 " RUNNING $end
$var wire 1 # INIT $end
$var wire 1 $ FINISH $end
$var wire 1 % BIST_END $end
$var reg 1 & CLK $end
$var reg 1 ' RESET $end
$var reg 1 ( START $end
$var integer 32 ) pulsecount [31:0] $end
$var integer 32 * runningcount [31:0] $end
$scope module uut $end
$var wire 1 % bist_end $end
$var wire 1 & clk $end
$var wire 1 + complete_c $end
$var wire 1 , latch_c $end
$var wire 1 - pass_fail $end
$var wire 1 ' reset $end
$var wire 1 " running $end
$var wire 1 ( start $end
$var wire 1 ! toggle $end
$var wire 1 # init $end
$var wire 1 $ finish $end
$var reg 1 . complete $end
$var reg 11 / ncounter [10:0] $end
$var reg 3 0 next_state [2:0] $end
$var reg 1 1 reset_latch $end
$var reg 3 2 state [2:0] $end
$var reg 1 3 toggle_r $end
$upscope $end
$upscope $end
$enddefinitions $end
#0
$dumpvars
x3
bx 2
x1
bx 0
bx /
x.
z-
0,
0+
b0 *
b0 )
0(
0'
0&
x%
x$
x#
x"
x!
$end
#1000
0%
1+
1,
1'
#5000
0.
b0 0
0"
0!
0#
0$
b0 2
b0 /
03
1&
#6000
0+
0,
0'
#10000
0&
#11000
01
1+
1,
1(
#15000
b10 0
b1 2
1&
#16000
0+
0,
0(
#20000
0&
#25000
b11 0
1#
b10 2
1&
#30000
0&
#35000
1"
0#
b11 2
1&
#40000
0&
#45000
b1 )
1!
b1 /
13
b1 *
1&
#50000
0&
#55000
0!
b10 /
03
b10 *
1&
#60000
0&
#65000
b10 )
1!
b11 /
13
b11 *
1&
#70000
0&
#75000
0!
b100 /
03
b100 *
1&
#80000
0&
#85000
b11 )
1!
b101 /
13
b101 *
1&
#90000
0&
#95000
0!
b110 /
03
b110 *
1&
#100000
0&
#105000
b100 )
1!
b111 /
13
b111 *
1&
#110000
0&
#115000
0!
b1000 /
03
b1000 *
1&
#120000
0&
#125000
b101 )
1!
b1001 /
13
b1001 *
1&
#130000
0&
#135000
0!
b1010 /
03
b1010 *
1&
#140000
0&
#145000
b110 )
1!
b1011 /
13
b1011 *
1&
#150000
0&
#155000
0!
b1100 /
03
b1100 *
1&
#160000
0&
#165000
b111 )
1!
b1101 /
13
b1101 *
1&
#170000
0&
#175000
0!
b1110 /
03
b1110 *
1&
#180000
0&
#185000
b1000 )
1!
b1111 /
13
b1111 *
1&
#190000
0&
#195000
0!
b10000 /
03
b10000 *
1&
#200000
0&
#205000
b1001 )
1!
b10001 /
13
b10001 *
1&
#210000
0&
#215000
0!
b10010 /
03
b10010 *
1&
#220000
0&
#225000
b1010 )
1!
b10011 /
13
b10011 *
1&
#230000
0&
#235000
0!
b10100 /
03
b10100 *
1&
#240000
0&
#245000
b1011 )
1!
b10101 /
13
b10101 *
1&
#250000
0&
#255000
0!
b10110 /
03
b10110 *
1&
#260000
0&
#265000
b1100 )
1!
b10111 /
13
b10111 *
1&
#270000
0&
#275000
0!
b11000 /
03
b11000 *
1&
#280000
0&
#285000
b1101 )
1!
b11001 /
13
b11001 *
1&
#290000
0&
#295000
0!
b11010 /
03
b11010 *
1&
#300000
0&
#305000
b1110 )
1!
b11011 /
13
b11011 *
1&
#310000
0&
#315000
0!
b11100 /
03
b11100 *
1&
#320000
0&
#325000
b1111 )
1!
b11101 /
13
b11101 *
1&
#330000
0&
#335000
0!
b11110 /
03
b11110 *
1&
#340000
0&
#345000
b10000 )
1!
b11111 /
13
b11111 *
1&
#350000
0&
#355000
0!
b100000 /
03
b100000 *
1&
#360000
0&
#365000
b10001 )
1!
b100001 /
13
b100001 *
1&
#370000
0&
#375000
0!
b100010 /
03
b100010 *
1&
#380000
0&
#385000
b10010 )
1!
b100011 /
13
b100011 *
1&
#390000
0&
#395000
0!
b100100 /
03
b100100 *
1&
#400000
0&
#405000
b10011 )
1!
b100101 /
13
b100101 *
1&
#410000
0&
#415000
0!
b100110 /
03
b100110 *
1&
#420000
0&
#425000
b10100 )
1!
b100111 /
13
b100111 *
1&
#430000
0&
#435000
0!
b101000 /
03
b101000 *
1&
#440000
0&
#445000
b10101 )
1!
b101001 /
13
b101001 *
1&
#450000
0&
#455000
0!
b101010 /
03
b101010 *
1&
#460000
0&
#465000
b10110 )
1!
b101011 /
13
b101011 *
1&
#470000
0&
#475000
0!
b101100 /
03
b101100 *
1&
#480000
0&
#485000
b10111 )
1!
b101101 /
13
b101101 *
1&
#490000
0&
#495000
0!
b101110 /
03
b101110 *
1&
#500000
0&
#505000
b11000 )
1!
b101111 /
13
b101111 *
1&
#510000
0&
#515000
0!
b110000 /
03
b110000 *
1&
#520000
0&
#525000
b11001 )
1!
b110001 /
13
b110001 *
1&
#530000
0&
#535000
0!
b110010 /
03
b110010 *
1&
#540000
0&
#545000
b11010 )
1!
b110011 /
13
b110011 *
1&
#550000
0&
#555000
0!
b110100 /
03
b110100 *
1&
#560000
0&
#565000
b11011 )
1!
b110101 /
13
b110101 *
1&
#570000
0&
#575000
0!
b110110 /
03
b110110 *
1&
#580000
0&
#585000
b11100 )
1!
b110111 /
13
b110111 *
1&
#590000
0&
#595000
0!
b111000 /
03
b111000 *
1&
#600000
0&
#605000
b11101 )
1!
b111001 /
13
b111001 *
1&
#610000
0&
#615000
0!
b111010 /
03
b111010 *
1&
#620000
0&
#625000
b11110 )
1!
b111011 /
13
b111011 *
1&
#630000
0&
#635000
0!
b111100 /
03
b111100 *
1&
#640000
0&
#645000
b11111 )
1!
b111101 /
13
b111101 *
1&
#650000
0&
#655000
0!
b111110 /
03
b111110 *
1&
#660000
0&
#665000
b100000 )
1!
b111111 /
13
b111111 *
1&
#670000
0&
#675000
0!
b1000000 /
03
b1000000 *
1&
#680000
0&
#685000
b100001 )
1!
b1000001 /
13
b1000001 *
1&
#690000
0&
#695000
0!
b1000010 /
03
b1000010 *
1&
#700000
0&
#705000
b100010 )
1!
b1000011 /
13
b1000011 *
1&
#710000
0&
#715000
0!
b1000100 /
03
b1000100 *
1&
#720000
0&
#725000
b100011 )
1!
b1000101 /
13
b1000101 *
1&
#730000
0&
#735000
0!
b1000110 /
03
b1000110 *
1&
#740000
0&
#745000
b100100 )
1!
b1000111 /
13
b1000111 *
1&
#750000
0&
#755000
0!
b1001000 /
03
b1001000 *
1&
#760000
0&
#765000
b100101 )
1!
b1001001 /
13
b1001001 *
1&
#770000
0&
#775000
0!
b1001010 /
03
b1001010 *
1&
#780000
0&
#785000
b100110 )
1!
b1001011 /
13
b1001011 *
1&
#790000
0&
#795000
0!
b1001100 /
03
b1001100 *
1&
#800000
0&
#805000
b100111 )
1!
b1001101 /
13
b1001101 *
1&
#810000
0&
#815000
0!
b1001110 /
03
b1001110 *
1&
#820000
0&
#825000
b101000 )
1!
b1001111 /
13
b1001111 *
1&
#830000
0&
#835000
0!
b1010000 /
03
b1010000 *
1&
#840000
0&
#845000
b101001 )
1!
b1010001 /
13
b1010001 *
1&
#850000
0&
#855000
0!
b1010010 /
03
b1010010 *
1&
#860000
0&
#865000
b101010 )
1!
b1010011 /
13
b1010011 *
1&
#870000
0&
#875000
0!
b1010100 /
03
b1010100 *
1&
#880000
0&
#885000
b101011 )
1!
b1010101 /
13
b1010101 *
1&
#890000
0&
#895000
0!
b1010110 /
03
b1010110 *
1&
#900000
0&
#905000
b101100 )
1!
b1010111 /
13
b1010111 *
1&
#910000
0&
#915000
0!
b1011000 /
03
b1011000 *
1&
#920000
0&
#925000
b101101 )
1!
b1011001 /
13
b1011001 *
1&
#930000
0&
#935000
0!
b1011010 /
03
b1011010 *
1&
#940000
0&
#945000
b101110 )
1!
b1011011 /
13
b1011011 *
1&
#950000
0&
#955000
0!
b1011100 /
03
b1011100 *
1&
#960000
0&
#965000
b101111 )
1!
b1011101 /
13
b1011101 *
1&
#970000
0&
#975000
0!
b1011110 /
03
b1011110 *
1&
#980000
0&
#985000
b110000 )
1!
b1011111 /
13
b1011111 *
1&
#990000
0&
#995000
0!
b1100000 /
03
b1100000 *
1&
#1000000
0&
#1005000
b110001 )
1!
b1100001 /
13
b1100001 *
1&
#1010000
0&
#1015000
0!
b1100010 /
03
b1100010 *
1&
#1020000
0&
#1025000
b110010 )
1!
b1100011 /
13
b1100011 *
1&
#1030000
0&
#1035000
0!
b1100100 /
03
b1100100 *
1&
#1040000
0&
#1045000
b110011 )
1!
b1100101 /
13
b1100101 *
1&
#1050000
0&
#1055000
0!
b1100110 /
03
b1100110 *
1&
#1060000
0&
#1065000
b110100 )
1!
b1100111 /
13
b1100111 *
1&
#1070000
0&
#1075000
0!
b1101000 /
03
b1101000 *
1&
#1080000
0&
#1085000
b110101 )
1!
b1101001 /
13
b1101001 *
1&
#1090000
0&
#1095000
0!
b1101010 /
03
b1101010 *
1&
#1100000
0&
#1105000
b110110 )
1!
b1101011 /
13
b1101011 *
1&
#1110000
0&
#1115000
0!
b1101100 /
03
b1101100 *
1&
#1120000
0&
#1125000
b110111 )
1!
b1101101 /
13
b1101101 *
1&
#1130000
0&
#1135000
0!
b1101110 /
03
b1101110 *
1&
#1140000
0&
#1145000
b111000 )
1!
b1101111 /
13
b1101111 *
1&
#1150000
0&
#1155000
0!
b1110000 /
03
b1110000 *
1&
#1160000
0&
#1165000
b111001 )
1!
b1110001 /
13
b1110001 *
1&
#1170000
0&
#1175000
0!
b1110010 /
03
b1110010 *
1&
#1180000
0&
#1185000
b111010 )
1!
b1110011 /
13
b1110011 *
1&
#1190000
0&
#1195000
0!
b1110100 /
03
b1110100 *
1&
#1200000
0&
#1205000
b111011 )
1!
b1110101 /
13
b1110101 *
1&
#1210000
0&
#1215000
0!
b1110110 /
03
b1110110 *
1&
#1220000
0&
#1225000
b111100 )
1!
b1110111 /
13
b1110111 *
1&
#1230000
0&
#1235000
0!
b1111000 /
03
b1111000 *
1&
#1240000
0&
#1245000
b111101 )
1!
b1111001 /
13
b1111001 *
1&
#1250000
0&
#1255000
0!
b1111010 /
03
b1111010 *
1&
#1260000
0&
#1265000
b111110 )
1!
b1111011 /
13
b1111011 *
1&
#1270000
0&
#1275000
0!
b1111100 /
03
b1111100 *
1&
#1280000
0&
#1285000
b111111 )
1!
b1111101 /
13
b1111101 *
1&
#1290000
0&
#1295000
0!
b1111110 /
03
b1111110 *
1&
#1300000
0&
#1305000
b1000000 )
1!
b1111111 /
13
b1111111 *
1&
#1310000
0&
#1315000
0!
b10000000 /
03
b10000000 *
1&
#1320000
0&
#1325000
b1000001 )
1!
b10000001 /
13
b10000001 *
1&
#1330000
0&
#1335000
0!
b10000010 /
03
b10000010 *
1&
#1340000
0&
#1345000
b1000010 )
1!
b10000011 /
13
b10000011 *
1&
#1350000
0&
#1355000
0!
b10000100 /
03
b10000100 *
1&
#1360000
0&
#1365000
b1000011 )
1!
b10000101 /
13
b10000101 *
1&
#1370000
0&
#1375000
0!
b10000110 /
03
b10000110 *
1&
#1380000
0&
#1385000
b1000100 )
1!
b10000111 /
13
b10000111 *
1&
#1390000
0&
#1395000
0!
b10001000 /
03
b10001000 *
1&
#1400000
0&
#1405000
b1000101 )
1!
b10001001 /
13
b10001001 *
1&
#1410000
0&
#1415000
0!
b10001010 /
03
b10001010 *
1&
#1420000
0&
#1425000
b1000110 )
1!
b10001011 /
13
b10001011 *
1&
#1430000
0&
#1435000
0!
b10001100 /
03
b10001100 *
1&
#1440000
0&
#1445000
b1000111 )
1!
b10001101 /
13
b10001101 *
1&
#1450000
0&
#1455000
0!
b10001110 /
03
b10001110 *
1&
#1460000
0&
#1465000
b1001000 )
1!
b10001111 /
13
b10001111 *
1&
#1470000
0&
#1475000
0!
b10010000 /
03
b10010000 *
1&
#1480000
0&
#1485000
b1001001 )
1!
b10010001 /
13
b10010001 *
1&
#1490000
0&
#1495000
0!
b10010010 /
03
b10010010 *
1&
#1500000
0&
#1505000
b1001010 )
1!
b10010011 /
13
b10010011 *
1&
#1510000
0&
#1515000
0!
b10010100 /
03
b10010100 *
1&
#1520000
0&
#1525000
b1001011 )
1!
b10010101 /
13
b10010101 *
1&
#1530000
0&
#1535000
0!
b10010110 /
03
b10010110 *
1&
#1540000
0&
#1545000
b1001100 )
1!
b10010111 /
13
b10010111 *
1&
#1550000
0&
#1555000
0!
b10011000 /
03
b10011000 *
1&
#1560000
0&
#1565000
b1001101 )
1!
b10011001 /
13
b10011001 *
1&
#1570000
0&
#1575000
0!
b10011010 /
03
b10011010 *
1&
#1580000
0&
#1585000
b1001110 )
1!
b10011011 /
13
b10011011 *
1&
#1590000
0&
#1595000
0!
b10011100 /
03
b10011100 *
1&
#1600000
0&
#1605000
b1001111 )
1!
b10011101 /
13
b10011101 *
1&
#1610000
0&
#1615000
0!
b10011110 /
03
b10011110 *
1&
#1620000
0&
#1625000
b1010000 )
1!
b10011111 /
13
b10011111 *
1&
#1630000
0&
#1635000
0!
b10100000 /
03
b10100000 *
1&
#1640000
0&
#1645000
b1010001 )
1!
b10100001 /
13
b10100001 *
1&
#1650000
0&
#1655000
0!
b10100010 /
03
b10100010 *
1&
#1660000
0&
#1665000
b1010010 )
1!
b10100011 /
13
b10100011 *
1&
#1670000
0&
#1675000
0!
b10100100 /
03
b10100100 *
1&
#1680000
0&
#1685000
b1010011 )
1!
b10100101 /
13
b10100101 *
1&
#1690000
0&
#1695000
0!
b10100110 /
03
b10100110 *
1&
#1700000
0&
#1705000
b1010100 )
1!
b10100111 /
13
b10100111 *
1&
#1710000
0&
#1715000
0!
b10101000 /
03
b10101000 *
1&
#1720000
0&
#1725000
b1010101 )
1!
b10101001 /
13
b10101001 *
1&
#1730000
0&
#1735000
0!
b10101010 /
03
b10101010 *
1&
#1740000
0&
#1745000
b1010110 )
1!
b10101011 /
13
b10101011 *
1&
#1750000
0&
#1755000
0!
b10101100 /
03
b10101100 *
1&
#1760000
0&
#1765000
b1010111 )
1!
b10101101 /
13
b10101101 *
1&
#1770000
0&
#1775000
0!
b10101110 /
03
b10101110 *
1&
#1780000
0&
#1785000
b1011000 )
1!
b10101111 /
13
b10101111 *
1&
#1790000
0&
#1795000
0!
b10110000 /
03
b10110000 *
1&
#1800000
0&
#1805000
b1011001 )
1!
b10110001 /
13
b10110001 *
1&
#1810000
0&
#1815000
0!
b10110010 /
03
b10110010 *
1&
#1820000
0&
#1825000
b1011010 )
1!
b10110011 /
13
b10110011 *
1&
#1830000
0&
#1835000
0!
b10110100 /
03
b10110100 *
1&
#1840000
0&
#1845000
b1011011 )
1!
b10110101 /
13
b10110101 *
1&
#1850000
0&
#1855000
0!
b10110110 /
03
b10110110 *
1&
#1860000
0&
#1865000
b1011100 )
1!
b10110111 /
13
b10110111 *
1&
#1870000
0&
#1875000
0!
b10111000 /
03
b10111000 *
1&
#1880000
0&
#1885000
b1011101 )
1!
b10111001 /
13
b10111001 *
1&
#1890000
0&
#1895000
0!
b10111010 /
03
b10111010 *
1&
#1900000
0&
#1905000
b1011110 )
1!
b10111011 /
13
b10111011 *
1&
#1910000
0&
#1915000
0!
b10111100 /
03
b10111100 *
1&
#1920000
0&
#1925000
b1011111 )
1!
b10111101 /
13
b10111101 *
1&
#1930000
0&
#1935000
0!
b10111110 /
03
b10111110 *
1&
#1940000
0&
#1945000
b1100000 )
1!
b10111111 /
13
b10111111 *
1&
#1950000
0&
#1955000
0!
b11000000 /
03
b11000000 *
1&
#1960000
0&
#1965000
b1100001 )
1!
b11000001 /
13
b11000001 *
1&
#1970000
0&
#1975000
0!
b11000010 /
03
b11000010 *
1&
#1980000
0&
#1985000
b1100010 )
1!
b11000011 /
13
b11000011 *
1&
#1990000
0&
#1995000
0!
b11000100 /
03
b11000100 *
1&
#2000000
0&
#2005000
b1100011 )
1!
b11000101 /
13
b11000101 *
1&
#2010000
0&
#2015000
0!
b11000110 /
03
b11000110 *
1&
#2020000
0&
#2025000
b1100100 )
1!
b11000111 /
13
b11000111 *
1&
#2030000
0&
#2035000
0!
b11001000 /
03
b11001000 *
1&
#2040000
0&
#2045000
b1100101 )
1!
b11001001 /
13
b11001001 *
1&
#2050000
0&
#2055000
0!
b11001010 /
03
b11001010 *
1&
#2060000
0&
#2065000
b1100110 )
1!
b11001011 /
13
b11001011 *
1&
#2070000
0&
#2075000
0!
b11001100 /
03
b11001100 *
1&
#2080000
0&
#2085000
b1100111 )
1!
b11001101 /
13
b11001101 *
1&
#2090000
0&
#2095000
0!
b11001110 /
03
b11001110 *
1&
#2100000
0&
#2105000
b1101000 )
1!
b11001111 /
13
b11001111 *
1&
#2110000
0&
#2115000
0!
b11010000 /
03
b11010000 *
1&
#2120000
0&
#2125000
b1101001 )
1!
b11010001 /
13
b11010001 *
1&
#2130000
0&
#2135000
0!
b11010010 /
03
b11010010 *
1&
#2140000
0&
#2145000
b1101010 )
1!
b11010011 /
13
b11010011 *
1&
#2150000
0&
#2155000
0!
b11010100 /
03
b11010100 *
1&
#2160000
0&
#2165000
b1101011 )
1!
b11010101 /
13
b11010101 *
1&
#2170000
0&
#2175000
0!
b11010110 /
03
b11010110 *
1&
#2180000
0&
#2185000
b1101100 )
1!
b11010111 /
13
b11010111 *
1&
#2190000
0&
#2195000
0!
b11011000 /
03
b11011000 *
1&
#2200000
0&
#2205000
b1101101 )
1!
b11011001 /
13
b11011001 *
1&
#2210000
0&
#2215000
0!
b11011010 /
03
b11011010 *
1&
#2220000
0&
#2225000
b1101110 )
1!
b11011011 /
13
b11011011 *
1&
#2230000
0&
#2235000
0!
b11011100 /
03
b11011100 *
1&
#2240000
0&
#2245000
b1101111 )
1!
b11011101 /
13
b11011101 *
1&
#2250000
0&
#2255000
0!
b11011110 /
03
b11011110 *
1&
#2260000
0&
#2265000
b1110000 )
1!
b11011111 /
13
b11011111 *
1&
#2270000
0&
#2275000
0!
b11100000 /
03
b11100000 *
1&
#2280000
0&
#2285000
b1110001 )
1!
b11100001 /
13
b11100001 *
1&
#2290000
0&
#2295000
0!
b11100010 /
03
b11100010 *
1&
#2300000
0&
#2305000
b1110010 )
1!
b11100011 /
13
b11100011 *
1&
#2310000
0&
#2315000
0!
b11100100 /
03
b11100100 *
1&
#2320000
0&
#2325000
b1110011 )
1!
b11100101 /
13
b11100101 *
1&
#2330000
0&
#2335000
0!
b11100110 /
03
b11100110 *
1&
#2340000
0&
#2345000
b1110100 )
1!
b11100111 /
13
b11100111 *
1&
#2350000
0&
#2355000
0!
b11101000 /
03
b11101000 *
1&
#2360000
0&
#2365000
b1110101 )
1!
b11101001 /
13
b11101001 *
1&
#2370000
0&
#2375000
0!
b11101010 /
03
b11101010 *
1&
#2380000
0&
#2385000
b1110110 )
1!
b11101011 /
13
b11101011 *
1&
#2390000
0&
#2395000
0!
b11101100 /
03
b11101100 *
1&
#2400000
0&
#2405000
b1110111 )
1!
b11101101 /
13
b11101101 *
1&
#2410000
0&
#2415000
0!
b11101110 /
03
b11101110 *
1&
#2420000
0&
#2425000
b1111000 )
1!
b11101111 /
13
b11101111 *
1&
#2430000
0&
#2435000
0!
b11110000 /
03
b11110000 *
1&
#2440000
0&
#2445000
b1111001 )
1!
b11110001 /
13
b11110001 *
1&
#2450000
0&
#2455000
0!
b11110010 /
03
b11110010 *
1&
#2460000
0&
#2465000
b1111010 )
1!
b11110011 /
13
b11110011 *
1&
#2470000
0&
#2475000
0!
b11110100 /
03
b11110100 *
1&
#2480000
0&
#2485000
b1111011 )
1!
b11110101 /
13
b11110101 *
1&
#2490000
0&
#2495000
0!
b11110110 /
03
b11110110 *
1&
#2500000
0&
#2505000
b1111100 )
1!
b11110111 /
13
b11110111 *
1&
#2510000
0&
#2515000
0!
b11111000 /
03
b11111000 *
1&
#2520000
0&
#2525000
b1111101 )
1!
b11111001 /
13
b11111001 *
1&
#2530000
0&
#2535000
0!
b11111010 /
03
b11111010 *
1&
#2540000
0&
#2545000
b1111110 )
1!
b11111011 /
13
b11111011 *
1&
#2550000
0&
#2555000
0!
b11111100 /
03
b11111100 *
1&
#2560000
0&
#2565000
b1111111 )
1!
b11111101 /
13
b11111101 *
1&
#2570000
0&
#2575000
0!
b11111110 /
03
b11111110 *
1&
#2580000
0&
#2585000
b10000000 )
1!
b11111111 /
13
b11111111 *
1&
#2590000
0&
#2595000
0!
b100000000 /
03
b100000000 *
1&
#2600000
0&
#2605000
b10000001 )
1!
b100000001 /
13
b100000001 *
1&
#2610000
0&
#2615000
0!
b100000010 /
03
b100000010 *
1&
#2620000
0&
#2625000
b10000010 )
1!
b100000011 /
13
b100000011 *
1&
#2630000
0&
#2635000
0!
b100000100 /
03
b100000100 *
1&
#2640000
0&
#2645000
b10000011 )
1!
b100000101 /
13
b100000101 *
1&
#2650000
0&
#2655000
0!
b100000110 /
03
b100000110 *
1&
#2660000
0&
#2665000
b10000100 )
1!
b100000111 /
13
b100000111 *
1&
#2670000
0&
#2675000
0!
b100001000 /
03
b100001000 *
1&
#2680000
0&
#2685000
b10000101 )
1!
b100001001 /
13
b100001001 *
1&
#2690000
0&
#2695000
0!
b100001010 /
03
b100001010 *
1&
#2700000
0&
#2705000
b10000110 )
1!
b100001011 /
13
b100001011 *
1&
#2710000
0&
#2715000
0!
b100001100 /
03
b100001100 *
1&
#2720000
0&
#2725000
b10000111 )
1!
b100001101 /
13
b100001101 *
1&
#2730000
0&
#2735000
0!
b100001110 /
03
b100001110 *
1&
#2740000
0&
#2745000
b10001000 )
1!
b100001111 /
13
b100001111 *
1&
#2750000
0&
#2755000
0!
b100010000 /
03
b100010000 *
1&
#2760000
0&
#2765000
b10001001 )
1!
b100010001 /
13
b100010001 *
1&
#2770000
0&
#2775000
0!
b100010010 /
03
b100010010 *
1&
#2780000
0&
#2785000
b10001010 )
1!
b100010011 /
13
b100010011 *
1&
#2790000
0&
#2795000
0!
b100010100 /
03
b100010100 *
1&
#2800000
0&
#2805000
b10001011 )
1!
b100010101 /
13
b100010101 *
1&
#2810000
0&
#2815000
0!
b100010110 /
03
b100010110 *
1&
#2820000
0&
#2825000
b10001100 )
1!
b100010111 /
13
b100010111 *
1&
#2830000
0&
#2835000
0!
b100011000 /
03
b100011000 *
1&
#2840000
0&
#2845000
b10001101 )
1!
b100011001 /
13
b100011001 *
1&
#2850000
0&
#2855000
0!
b100011010 /
03
b100011010 *
1&
#2860000
0&
#2865000
b10001110 )
1!
b100011011 /
13
b100011011 *
1&
#2870000
0&
#2875000
0!
b100011100 /
03
b100011100 *
1&
#2880000
0&
#2885000
b10001111 )
1!
b100011101 /
13
b100011101 *
1&
#2890000
0&
#2895000
0!
b100011110 /
03
b100011110 *
1&
#2900000
0&
#2905000
b10010000 )
1!
b100011111 /
13
b100011111 *
1&
#2910000
0&
#2915000
0!
b100100000 /
03
b100100000 *
1&
#2920000
0&
#2925000
b10010001 )
1!
b100100001 /
13
b100100001 *
1&
#2930000
0&
#2935000
0!
b100100010 /
03
b100100010 *
1&
#2940000
0&
#2945000
b10010010 )
1!
b100100011 /
13
b100100011 *
1&
#2950000
0&
#2955000
0!
b100100100 /
03
b100100100 *
1&
#2960000
0&
#2965000
b10010011 )
1!
b100100101 /
13
b100100101 *
1&
#2970000
0&
#2975000
0!
b100100110 /
03
b100100110 *
1&
#2980000
0&
#2985000
b10010100 )
1!
b100100111 /
13
b100100111 *
1&
#2990000
0&
#2995000
0!
b100101000 /
03
b100101000 *
1&
#3000000
0&
#3005000
b10010101 )
1!
b100101001 /
13
b100101001 *
1&
#3010000
0&
#3015000
0!
b100101010 /
03
b100101010 *
1&
#3020000
0&
#3025000
b10010110 )
1!
b100101011 /
13
b100101011 *
1&
#3030000
0&
#3035000
0!
b100101100 /
03
b100101100 *
1&
#3040000
0&
#3045000
b10010111 )
1!
b100101101 /
13
b100101101 *
1&
#3050000
0&
#3055000
0!
b100101110 /
03
b100101110 *
1&
#3060000
0&
#3065000
b10011000 )
1!
b100101111 /
13
b100101111 *
1&
#3070000
0&
#3075000
0!
b100110000 /
03
b100110000 *
1&
#3080000
0&
#3085000
b10011001 )
1!
b100110001 /
13
b100110001 *
1&
#3090000
0&
#3095000
0!
b100110010 /
03
b100110010 *
1&
#3100000
0&
#3105000
b10011010 )
1!
b100110011 /
13
b100110011 *
1&
#3110000
0&
#3115000
0!
b100110100 /
03
b100110100 *
1&
#3120000
0&
#3125000
b10011011 )
1!
b100110101 /
13
b100110101 *
1&
#3130000
0&
#3135000
0!
b100110110 /
03
b100110110 *
1&
#3140000
0&
#3145000
b10011100 )
1!
b100110111 /
13
b100110111 *
1&
#3150000
0&
#3155000
0!
b100111000 /
03
b100111000 *
1&
#3160000
0&
#3165000
b10011101 )
1!
b100111001 /
13
b100111001 *
1&
#3170000
0&
#3175000
0!
b100111010 /
03
b100111010 *
1&
#3180000
0&
#3185000
b10011110 )
1!
b100111011 /
13
b100111011 *
1&
#3190000
0&
#3195000
0!
b100111100 /
03
b100111100 *
1&
#3200000
0&
#3205000
b10011111 )
1!
b100111101 /
13
b100111101 *
1&
#3210000
0&
#3215000
0!
b100111110 /
03
b100111110 *
1&
#3220000
0&
#3225000
b10100000 )
1!
b100111111 /
13
b100111111 *
1&
#3230000
0&
