Project2/lfsr.v
// parameter seeed = 4'b1111;

module lfsr #
(   
    parameter NBIT = 4
) (
    input clk,
    input rst,
    input scan_in,
    input [3:0] seed, //this should be replaced after testing with a parameter
    output [3:0] out,
    output scan_out
);


    reg [NBIT-1:0] dff;

    assign out[0] = dff[0];
    assign out[1] = dff[1];
    assign out[2] = dff[2];
    assign out[3] = dff[3];
    
    assign scan_out = dff[3];




    always @ (posedge clk) begin
        if(rst) begin
            dff <= seed;
        end
        else begin
            dff <= {dff[NBIT-2:0], dff[3] ^ dff[2] ^ scan_in};
        end

    end

endmodule

Project2/Submission/Code/lfsr_test_tb.v
`timescale 1ns / 1ps

module lfsr_test_tb;
    integer start = 0;
    integer seed = 0;
    integer in_seed = 4'b0011;
    integer niter = 0;
    integer done = 0;
    wire [3:0] lfsr_out_w;
    reg reset;
    reg clock;
    reg [3:0] out_read;

    lfsr uut(
        .clk(clock),
        .rst(reset),
        .seed(in_seed),
        .out(lfsr_out_w),
        .scan_in(0)
    );


    initial begin
        $dumpfile("lsfr_test.vcd");
        $dumpvars();
        clock = 0;
        reset = 0;
    end

    initial begin
        #1;
        reset = 1;
        #3
        reset = 0;
        seed = lfsr_out_w;
        $display("Initial seed: %d" , seed);
        start = 1;
        wait (done == 1)
        $display("End in %d iterations" ,niter);
        $display("Should be 2^4-1 = %d" ,2**4-1);
    end

    always @ (posedge clock) begin
        if(start) begin
            if(lfsr_out_w == seed && niter != 0) begin
                done = 1;
                start = 0;
            end
            else begin
                $display("LFSR output: %d" ,lfsr_out_w);
                niter++;  
            end
        end
    end

    initial begin
        #100 $finish;
    end

    always
        #2  clock =  ! clock;

endmodule

Project2/lsfr_test.vcd
$date
	Mon May 18 15:52:07 2020
$end
$version
	Icarus Verilog
$end
$timescale
	1ps
$end
$scope module lfsr_test_tb $end
$var wire 4 ! lfsr_out_w [3:0] $end
$var reg 1 " clock $end
$var reg 1 # reset $end
$var integer 32 $ done [31:0] $end
$var integer 32 % in_seed [31:0] $end
$var integer 32 & niter [31:0] $end
$var integer 32 ' seed [31:0] $end
$var integer 32 ( start [31:0] $end
$scope module uut $end
$var wire 1 " clk $end
$var wire 1 # rst $end
$var wire 1 ) scan_in $end
$var wire 1 * scan_out $end
$var wire 4 + seed [3:0] $end
$var wire 4 , out [3:0] $end
$var reg 4 - dff [3:0] $end
$upscope $end
$upscope $end
$enddefinitions $end
#0
$dumpvars
bx -
bx ,
b11 +
z*
z)
b0 (
b0 '
b0 &
b11 %
b0 $
0#
0"
bx !
$end
#1000
1#
#2000
b11 !
b11 ,
b11 -
1"
#4000
0"
b1 (
b11 '
0#
#6000
b110 !
b110 ,
b110 -
b1 &
1"
#8000
0"
#10000
b1101 !
b1101 ,
b1101 -
b10 &
1"
#12000
0"
#14000
b1010 !
b1010 ,
b1010 -
b11 &
1"
#16000
0"
#18000
b101 !
b101 ,
b101 -
b100 &
1"
#20000
0"
#22000
b1011 !
b1011 ,
b1011 -
b101 &
1"
#24000
0"
#26000
b111 !
b111 ,
b111 -
b110 &
1"
#28000
0"
#30000
b1111 !
b1111 ,
b1111 -
b111 &
1"
#32000
0"
#34000
b1110 !
b1110 ,
b1110 -
b1000 &
1"
#36000
0"
#38000
b1100 !
b1100 ,
b1100 -
b1001 &
1"
#40000
0"
#42000
b1000 !
b1000 ,
b1000 -
b1010 &
1"
#44000
0"
#46000
b1 !
b1 ,
b1 -
b1011 &
1"
#48000
0"
#50000
b10 !
b10 ,
b10 -
b1100 &
1"
#52000
0"
#54000
b100 !
b100 ,
b100 -
b1101 &
1"
#56000
0"
#58000
b1001 !
b1001 ,
b1001 -
b1110 &
1"
#60000
0"
#62000
b11 !
b11 ,
b11 -
b1111 &
1"
#64000
0"
#66000
b110 !
b110 ,
b110 -
b0 (
b1 $
1"
#68000
0"
#70000
b1101 !
b1101 ,
b1101 -
1"
#72000
0"
#74000
b1010 !
b1010 ,
b1010 -
1"
#76000
0"
#78000
b101 !
b101 ,
b101 -
1"
#80000
0"
#82000
b1011 !
b1011 ,
b1011 -
1"
#84000
0"
#86000
b111 !
b111 ,
b111 -
1"
#88000
0"
#90000
b1111 !
b1111 ,
b1111 -
1"
#92000
0"
#94000
b1110 !
b1110 ,
b1110 -
1"
#96000
0"
#98000
b1100 !
b1100 ,
b1100 -
1"
