Project2/misr.v
module misr(
    input clk,
    input rst,
    input scan_in,
    input[3:0] grant_o,
    output[NBIT-1:0] signature,
    output scan_out
);

    parameter NBIT = 6;
    parameter seed = 6'b111111;
    reg [NBIT-1:0] dff;

    assign signature = dff;

    always @ (posedge clk) begin
        if(rst) begin
            dff <= seed;
        end
        else begin
            dff[0] <= grant_o[3] ^ dff[NBIT-1];          
            dff[1] <= grant_o[2] ^ dff[0];
            dff[2] <= grant_o[1] ^ dff[1]; 
            dff[3] <= grant_o[0] ^ dff[2]; 
            dff[4] <=              dff[3];
            dff[5] <=              dff[4] ^ dff[NBIT-1];
        end
    end

endmodule

Project2/lfsr.v
// parameter seeed = 4'b1111;

module lfsr #
(   
    parameter NBIT = 4
) (
    input clk,
    input rst,
    input scan_in,
    input [3:0] seed, //this should be replaced after testing with a parameter
    output [3:0] out,
    output scan_out
);


    reg [NBIT-1:0] dff;

    assign out[0] = dff[0];
    assign out[1] = dff[1];
    assign out[2] = dff[2];
    assign out[3] = dff[3];
    
    assign scan_out = dff[3];




    always @ (posedge clk) begin
        if(rst) begin
            dff <= seed;
        end
        else begin
            dff <= {dff[NBIT-2:0], dff[3] ^ dff[2] ^ scan_in};
        end

    end

endmodule

Project2/misr_test_tb2.v
`timescale 1ns / 1ps

module misr_test_tb;
    integer start = 0;
    integer seed = 0;
    integer in_seed = 4'b0001;
    integer niter = 0;
    integer done = 0;
    integer signature_result = 0;
    wire [3:0] signature_out_w;
    wire [3:0] lfsr_out_w;
    reg reset;
    reg clock;
    reg [3:0] out_read;

    lfsr lfsr1(
        .clk(clock),
        .rst(reset),
        .seed(in_seed),
        .out(lfsr_out_w)
    );

    misr uut(
        .clk(clock),
        .rst(reset),
        .grant_o(lfsr_out_w),
        .signature(signature_out_w)
    );


    initial begin
        $dumpfile("misr_test.vcd");
        $dumpvars();
        clock = 0;
        reset = 0;
    end

    initial begin
        for(in_seed = 4'b0001; in_seed<=4'b1111; in_seed=in_seed+1) begin
            wait (!clock)
            #1;
            reset = 1;
            #3
            reset = 0;
            seed = lfsr_out_w;
            // $display("Initial seed: %d", in_seed);
            start = 1;
            wait (done == 1)
            // $display("End in %d iterations", niter);
            signature_result = signature_out_w;
            $display("Final misr signature for seed %d = %d", in_seed, signature_out_w);
            done = 0;
            niter = 0;
            
        end
        // $finish;
    end

    always @ (*) begin
        if(start) begin
            if(lfsr_out_w == in_seed && niter != 0) begin
                done = 1;
                start = 0;
            end
            else begin
                // $display("Current signature: %d" ,signature_out_w); only for debug
                niter++;  
            end
        end
    end

    initial begin
        #3000 $finish;
    end

    always
        #2  clock =  ! clock;

endmodule

Project2/misr_test.vcd
$date
	Mon May 18 15:48:33 2020
$end
$version
	Icarus Verilog
$end
$timescale
	1ps
$end
$scope module misr_test_tb $end
$var wire 4 ! signature_out_w [3:0] $end
$var wire 4 " lfsr_out_w [3:0] $end
$var reg 1 # clock $end
$var reg 1 $ reset $end
$var integer 32 % done [31:0] $end
$var integer 32 & in_seed [31:0] $end
$var integer 32 ' niter [31:0] $end
$var integer 32 ( seed [31:0] $end
$var integer 32 ) signature_result [31:0] $end
$var integer 32 * start [31:0] $end
$scope module lfsr1 $end
$var wire 1 # clk $end
$var wire 1 $ rst $end
$var wire 1 + scan_in $end
$var wire 1 , scan_out $end
$var wire 4 - seed [3:0] $end
$var wire 4 . out [3:0] $end
$var reg 4 / dff [3:0] $end
$upscope $end
$scope module uut $end
$var wire 1 # clk $end
$var wire 4 0 grant_o [3:0] $end
$var wire 1 $ rst $end
$var wire 1 1 scan_in $end
$var wire 1 2 scan_out $end
$var wire 6 3 signature [5:0] $end
$var reg 6 4 dff [5:0] $end
$upscope $end
$upscope $end
$enddefinitions $end
#0
$dumpvars
bx 4
bx 3
z2
z1
bx 0
bx /
bx .
b1 -
z,
z+
b0 *
b0 )
b0 (
b0 '
b1 &
b0 %
0$
0#
bx "
bx !
$end
#1000
1$
#2000
b1 "
b1 .
b1 0
b1111 !
b1 /
b111111 3
b111111 4
1#
#4000
b1 '
0#
b1 *
b1 (
0$
#6000
b10 '
b111 !
b10 "
b10 .
b10 0
b10111 3
b10111 4
b10 /
1#
#8000
0#
#10000
b11 '
b100 "
b100 .
b100 0
b1010 !
b100 /
b101010 3
b101010 4
1#
#12000
0#
#14000
b100 '
b111 !
b1001 "
b1001 .
b1001 0
b110111 3
b110111 4
b1001 /
1#
#16000
0#
#18000
b101 '
b11 "
b11 .
b11 0
b110 !
b11 /
b110 3
b110 4
1#
#20000
0#
#22000
b110 '
b0 !
b110 "
b110 .
b110 0
b0 3
b0 4
b110 /
1#
#24000
0#
#26000
b111 '
b1101 "
b1101 .
b1101 0
b110 !
b1101 /
b110 3
b110 4
1#
#28000
0#
#30000
b1000 '
b111 !
b1010 "
b1010 .
b1010 0
b111 3
b111 4
b1010 /
1#
#32000
0#
#34000
b1001 '
b101 "
b101 .
b101 0
b1011 !
b101 /
b1011 3
b1011 4
1#
#36000
0#
#38000
b1010 '
b1100 !
b1011 "
b1011 .
b1011 0
b11100 3
b11100 4
b1011 /
1#
#40000
0#
#42000
b1011 '
b111 "
b111 .
b111 0
b101 !
b111 /
b110101 3
b110101 4
1#
#44000
0#
#46000
b1100 '
b1111 "
b1111 .
b1111 0
b101 3
b101 4
b1111 /
1#
#48000
0#
#50000
b1101 '
b1110 "
b1110 .
b1110 0
b1110 /
1#
#52000
0#
#54000
b1110 '
b1101 !
b1100 "
b1100 .
b1100 0
b1101 3
b1101 4
b1100 /
1#
#56000
0#
#58000
b1111 '
b1000 "
b1000 .
b1000 0
b1001 !
b1000 /
b11001 3
b11001 4
1#
#60000
0#
#62000
b10 -
b10 &
b0 '
b11 )
b0 *
b0 %
b11 !
b1 "
b1 .
b1 0
b110011 3
b110011 4
b1 /
1#
#64000
0#
#65000
1$
#66000
b10 "
b10 .
b10 0
b1111 !
b10 /
b111111 3
b111111 4
1#
#68000
b1 '
0#
b1 *
b10 (
0$
#70000
b10 '
b1011 !
b100 "
b100 .
b100 0
b11011 3
b11011 4
b100 /
1#
#72000
0#
#74000
b11 '
b1001 "
b1001 .
b1001 0
b100 !
b1001 /
b110100 3
b110100 4
1#
#76000
0#
#78000
b100 '
b0 !
b11 "
b11 .
b11 0
b0 3
b0 4
b11 /
1#
#80000
0#
#82000
b101 '
b110 "
b110 .
b110 0
b1100 !
b110 /
b1100 3
b1100 4
1#
#84000
0#
#86000
b110 '
b1110 !
b1101 "
b1101 .
b1101 0
b11110 3
b11110 4
b1101 /
1#
#88000
0#
#90000
b111 '
b1010 "
b1010 .
b1010 0
b111 !
b1010 /
b110111 3
b110111 4
1#
#92000
0#
#94000
b1000 '
b1010 !
b101 "
b101 .
b101 0
b1010 3
b1010 4
b101 /
1#
#96000
0#
#98000
b1001 '
b1011 "
b1011 .
b1011 0
b1110 !
b1011 /
b11110 3
b11110 4
1#
#100000
0#
#102000
b1010 '
b1 !
b111 "
b111 .
b111 0
b110001 3
b110001 4
b111 /
1#
#104000
0#
#106000
b1011 '
b1111 "
b1111 .
b1111 0
b1101 !
b1111 /
b1101 3
b1101 4
1#
#108000
0#
#110000
b1100 '
b101 !
b1110 "
b1110 .
b1110 0
b10101 3
b10101 4
b1110 /
1#
#112000
0#
#114000
b1101 '
b1100 "
b1100 .
b1100 0
b1101 !
b1100 /
b101101 3
b101101 4
1#
#116000
0#
#118000
b1110 '
b1000 !
b1000 "
b1000 .
b1000 0
b111000 3
b111000 4
b1000 /
1#
#120000
0#
#122000
b1111 '
b1 "
b1 .
b1 0
b0 !
b1 /
b10000 3
b10000 4
1#
#124000
0#
#126000
b11 -
b11 &
b0 '
b1000 )
b0 *
b0 %
b1000 !
b10 "
b10 .
b10 0
b101000 3
b101000 4
b10 /
1#
#128000
0#
#129000
1$
#130000
b11 "
b11 .
b11 0
b1111 !
b11 /
b111111 3
b111111 4
1#
#132000
b1 '
0#
b1 *
b11 (
0$
#134000
b10 '
b11 !
b110 "
b110 .
b110 0
b10011 3
b10011 4
b110 /
1#
#136000
0#
#138000
b11 '
b1101 "
b1101 .
b1101 0
b0 !
b1101 /
b100000 3
b100000 4
1#
#140000
0#
#142000
b100 '
b1010 !
b1010 "
b1010 .
b1010 0
b101010 3
b101010 4
b1010 /
1#
#144000
0#
#146000
b101 '
b101 "
b101 .
b101 0
b0 !
b101 /
b110000 3
b110000 4
1#
#148000
0#
#150000
b110 '
b1011 !
b1011 "
b1011 .
b1011 0
b1011 3
b1011 4
b1011 /
1#
#152000
0#
#154000
b111 '
b111 "
b111 .
b111 0
b111 /
b11011 3
b11011 4
1#
#156000
0#
#158000
b1000 '
b1000 !
b1111 "
b1111 .
b1111 0
b111000 3
b111000 4
b1111 /
1#
#160000
0#
#162000
b1001 '
b1110 "
b1110 .
b1110 0
b1110 !
b1110 /
b11110 3
b11110 4
1#
#164000
0#
#166000
b1010 '
b1011 !
b1100 "
b1100 .
b1100 0
b111011 3
b111011 4
b1100 /
1#
#168000
0#
#170000
b1011 '
b1000 "
b1000 .
b1000 0
b100 !
b1000 /
b10100 3
b10100 4
1#
#172000
0#
#174000
b1100 '
b1001 !
b1 "
b1 .
b1 0
b101001 3
b101001 4
b1 /
1#
#176000
0#
#178000
b1101 '
b10 "
b10 .
b10 0
b1011 !
b10 /
b111011 3
b111011 4
1#
#180000
0#
#182000
b1110 '
b11 !
b100 "
b100 .
b100 0
b10011 3
b10011 4
b100 /
1#
#184000
0#
#186000
b1111 '
b1001 "
b1001 .
b1001 0
b100 !
b1001 /
b100100 3
b100100 4
1#
#188000
0#
#190000
b100 -
b100 &
b0 '
b0 )
b0 *
b0 %
b0 !
b11 "
b11 .
b11 0
b100000 3
b100000 4
b11 /
1#
#192000
0#
#193000
1$
#194000
b100 "
b100 .
b100 0
b1111 !
b100 /
b111111 3
b111111 4
1#
#196000
b1 '
0#
b1 *
b100 (
0$
#198000
b10 '
b1101 !
b1001 "
b1001 .
b1001 0
b11101 3
b11101 4
b1001 /
1#
#200000
0#
#202000
b11 '
b11 "
b11 .
b11 0
b11 !
b11 /
b110011 3
b110011 4
1#
#204000
0#
#206000
b100 '
b1011 !
b110 "
b110 .
b110 0
b1011 3
b1011 4
b110 /
1#
#208000
0#
#210000
b101 '
b1101 "
b1101 .
b1101 0
b0 !
b1101 /
b10000 3
b10000 4
1#
#212000
0#
#214000
b110 '
b1011 !
b1010 "
b1010 .
b1010 0
b101011 3
b101011 4
b1010 /
1#
#216000
0#
#218000
b111 '
b101 "
b101 .
b101 0
b10 !
b101 /
b110010 3
b110010 4
1#
#220000
0#
#222000
b1000 '
b1111 !
b1011 "
b1011 .
b1011 0
b1111 3
b1111 4
b1011 /
1#
#224000
0#
#226000
b1001 '
b111 "
b111 .
b111 0
b11 !
b111 /
b10011 3
b10011 4
1#
#228000
0#
#230000
b1010 '
b1000 !
b1111 "
b1111 .
b1111 0
b101000 3
b101000 4
b1111 /
1#
#232000
0#
#234000
b1011 '
b1110 "
b1110 .
b1110 0
b1110 !
b1110 /
b111110 3
b111110 4
1#
#236000
0#
#238000
b1100 '
b1010 !
b1100 "
b1100 .
b1100 0
b11010 3
b11010 4
b1100 /
1#
#240000
0#
#242000
b1101 '
b1000 "
b1000 .
b1000 0
b111 !
b1000 /
b110111 3
b110111 4
1#
#244000
0#
#246000
b1110 '
b1110 !
b1 "
b1 .
b1 0
b1110 3
b1110 4
b1 /
1#
#248000
0#
#250000
b1111 '
b10 "
b10 .
b10 0
b100 !
b10 /
b10100 3
b10100 4
1#
#252000
0#
#254000
b101 -
b101 &
b0 '
b1100 )
b0 *
b0 %
b1100 !
b100 "
b100 .
b100 0
b101100 3
b101100 4
b100 /
1#
#256000
0#
#257000
1$
#258000
b101 "
b101 .
b101 0
b1111 !
b101 /
b111111 3
b111111 4
1#
#260000
b1 '
0#
b1 *
b101 (
0$
#262000
b10 '
b101 !
b1011 "
b1011 .
b1011 0
b10101 3
b10101 4
b1011 /
1#
#264000
0#
#266000
b11 '
b111 "
b111 .
b111 0
b111 !
b111 /
b100111 3
b100111 4
1#
#268000
0#
#270000
b100 '
b1 !
b1111 "
b1111 .
b1111 0
b100001 3
b100001 4
b1111 /
1#
#272000
0#
#274000
b101 '
b1110 "
b1110 .
b1110 0
b1100 !
b1110 /
b101100 3
b101100 4
1#
#276000
0#
#278000
b110 '
b1110 !
b1100 "
b1100 .
b1100 0
b111110 3
b111110 4
b1100 /
1#
#280000
0#
#282000
b111 '
b1000 "
b1000 .
b1000 0
b1000 /
b11110 3
b11110 4
1#
#284000
0#
#286000
b1000 '
b1101 !
b1 "
b1 .
b1 0
b111101 3
b111101 4
b1 /
1#
#288000
0#
#290000
b1001 '
b10 "
b10 .
b10 0
b11 !
b10 /
b10011 3
b10011 4
1#
#292000
0#
#294000
b1010 '
b10 !
b100 "
b100 .
b100 0
b100010 3
b100010 4
b100 /
1#
#296000
0#
#298000
b1011 '
b1001 "
b1001 .
b1001 0
b111 !
b1001 /
b100111 3
b100111 4
1#
#300000
0#
#302000
b1100 '
b110 !
b11 "
b11 .
b11 0
b100110 3
b100110 4
b11 /
1#
#304000
0#
#306000
b1101 '
b110 "
b110 .
b110 0
b1 !
b110 /
b100001 3
b100001 4
1#
#308000
0#
#310000
b1110 '
b101 !
b1101 "
b1101 .
b1101 0
b100101 3
b100101 4
b1101 /
1#
#312000
0#
#314000
b1111 '
b1010 "
b1010 .
b1010 0
b0 !
b1010 /
b100000 3
b100000 4
1#
#316000
0#
#318000
b110 -
b110 &
b0 '
b100 )
b0 *
b0 %
b100 !
b101 "
b101 .
b101 0
b100100 3
b100100 4
b101 /
1#
#320000
0#
#321000
1$
#322000
b110 "
b110 .
b110 0
b1111 !
b110 /
b111111 3
b111111 4
1#
#324000
b1 '
0#
b1 *
b110 (
0$
#326000
b10 '
b1001 !
b1101 "
b1101 .
b1101 0
b11001 3
b11001 4
b1101 /
1#
#328000
0#
#330000
b11 '
b1010 "
b1010 .
b1010 0
b1010 /
b111001 3
b111001 4
1#
#332000
0#
#334000
b100 '
b110 !
b101 "
b101 .
b101 0
b10110 3
b10110 4
b101 /
1#
#336000
0#
#338000
b101 '
b1011 "
b1011 .
b1011 0
b1011 /
b100110 3
b100110 4
1#
#340000
0#
#342000
b110 '
b0 !
b111 "
b111 .
b111 0
b100000 3
b100000 4
b111 /
1#
#344000
0#
#346000
b111 '
b1111 "
b1111 .
b1111 0
b1111 !
b1111 /
b101111 3
b101111 4
1#
#348000
0#
#350000
b1000 '
b0 !
b1110 "
b1110 .
b1110 0
b110000 3
b110000 4
b1110 /
1#
#352000
0#
#354000
b1001 '
b1100 "
b1100 .
b1100 0
b110 !
b1100 /
b110 3
b110 4
1#
#356000
0#
#358000
b1010 '
b1111 !
b1000 "
b1000 .
b1000 0
b1111 3
b1111 4
b1000 /
1#
#360000
0#
#362000
b1011 '
b1 "
b1 .
b1 0
b1 /
b11111 3
b11111 4
1#
#364000
0#
#366000
b1100 '
b110 !
b10 "
b10 .
b10 0
b110110 3
b110110 4
b10 /
1#
#368000
0#
#370000
b1101 '
b100 "
b100 .
b100 0
b1001 !
b100 /
b1001 3
b1001 4
1#
#372000
0#
#374000
b1110 '
b0 !
b1001 "
b1001 .
b1001 0
b10000 3
b10000 4
b1001 /
1#
#376000
0#
#378000
b1111 '
b11 "
b11 .
b11 0
b1001 !
b11 /
b101001 3
b101001 4
1#
#380000
0#
#382000
b111 -
b111 &
b0 '
b1111 )
b0 *
b0 %
b1111 !
b110 "
b110 .
b110 0
b111111 3
b111111 4
b110 /
1#
#384000
0#
#385000
1$
#386000
b111 "
b111 .
b111 0
b111 /
1#
#388000
b1 '
0#
b1 *
b111 (
0$
#390000
b10 '
b1 !
b1111 "
b1111 .
b1111 0
b10001 3
b10001 4
b1111 /
1#
#392000
0#
#394000
b11 '
b1110 "
b1110 .
b1110 0
b1101 !
b1110 /
b101101 3
b101101 4
1#
#396000
0#
#398000
b100 '
b1100 !
b1100 "
b1100 .
b1100 0
b111100 3
b111100 4
b1100 /
1#
#400000
0#
#402000
b101 '
b1000 "
b1000 .
b1000 0
b1010 !
b1000 /
b11010 3
b11010 4
1#
#404000
0#
#406000
b110 '
b101 !
b1 "
b1 .
b1 0
b110101 3
b110101 4
b1 /
1#
#408000
0#
#410000
b111 '
b10 "
b10 .
b10 0
b11 !
b10 /
b11 3
b11 4
1#
#412000
0#
#414000
b1000 '
b10 !
b100 "
b100 .
b100 0
b10 3
b10 4
b100 /
1#
#416000
0#
#418000
b1001 '
b1001 "
b1001 .
b1001 0
b110 !
b1001 /
b110 3
b110 4
1#
#420000
0#
#422000
b1010 '
b101 !
b11 "
b11 .
b11 0
b101 3
b101 4
b11 /
1#
#424000
0#
#426000
b1011 '
b110 "
b110 .
b110 0
b110 !
b110 /
b110 3
b110 4
1#
#428000
0#
#430000
b1100 '
b1010 !
b1101 "
b1101 .
b1101 0
b1010 3
b1010 4
b1101 /
1#
#432000
0#
#434000
b1101 '
b1010 "
b1010 .
b1010 0
b1111 !
b1010 /
b11111 3
b11111 4
1#
#436000
0#
#438000
b1110 '
b1011 !
b101 "
b101 .
b101 0
b111011 3
b111011 4
b101 /
1#
#440000
0#
#442000
b1111 '
b1011 "
b1011 .
b1011 0
b1101 !
b1011 /
b11101 3
b11101 4
1#
#444000
0#
#446000
b1000 -
b1000 &
b0 '
b111 )
b0 *
b0 %
b111 !
b111 "
b111 .
b111 0
b110111 3
b110111 4
b111 /
1#
#448000
0#
#449000
1$
#450000
b1000 "
b1000 .
b1000 0
b1111 !
b1000 /
b111111 3
b111111 4
1#
#452000
b1 '
0#
b1 *
b1000 (
0$
#454000
b10 '
b1110 !
b1 "
b1 .
b1 0
b11110 3
b11110 4
b1 /
1#
#456000
0#
#458000
b11 '
b10 "
b10 .
b10 0
b100 !
b10 /
b110100 3
b110100 4
1#
#460000
0#
#462000
b100 '
b1101 !
b100 "
b100 .
b100 0
b1101 3
b1101 4
b100 /
1#
#464000
0#
#466000
b101 '
b1001 "
b1001 .
b1001 0
b1000 !
b1001 /
b11000 3
b11000 4
1#
#468000
0#
#470000
b110 '
b1001 !
b11 "
b11 .
b11 0
b111001 3
b111001 4
b11 /
1#
#472000
0#
#474000
b111 '
b110 "
b110 .
b110 0
b1111 !
b110 /
b11111 3
b11111 4
1#
#476000
0#
#478000
b1000 '
b1000 !
b1101 "
b1101 .
b1101 0
b111000 3
b111000 4
b1101 /
1#
#480000
0#
#482000
b1001 '
b1010 "
b1010 .
b1010 0
b1010 !
b1010 /
b11010 3
b11010 4
1#
#484000
0#
#486000
b1010 '
b1 !
b101 "
b101 .
b101 0
b110001 3
b110001 4
b101 /
1#
#488000
0#
#490000
b1011 '
b1011 "
b1011 .
b1011 0
b1001 !
b1011 /
b1001 3
b1001 4
1#
#492000
0#
#494000
b1100 '
b1111 !
b111 "
b111 .
b111 0
b11111 3
b11111 4
b111 /
1#
#496000
0#
#498000
b1101 '
b1111 "
b1111 .
b1111 0
b0 !
b1111 /
b110000 3
b110000 4
1#
#500000
0#
#502000
b1110 '
b1110 !
b1110 "
b1110 .
b1110 0
b1110 3
b1110 4
b1110 /
1#
#504000
0#
#506000
b1111 '
b1100 "
b1100 .
b1100 0
b1011 !
b1100 /
b11011 3
b11011 4
1#
#508000
0#
#510000
b1001 -
b1001 &
b0 '
b101 )
b0 *
b0 %
b101 !
b1000 "
b1000 .
b1000 0
b110101 3
b110101 4
b1000 /
1#
#512000
0#
#513000
1$
#514000
b1001 "
b1001 .
b1001 0
b1111 !
b1001 /
b111111 3
b111111 4
1#
#516000
b1 '
0#
b1 *
b1001 (
0$
#518000
b10 '
b110 !
b11 "
b11 .
b11 0
b10110 3
b10110 4
b11 /
1#
#520000
0#
#522000
b11 '
b110 "
b110 .
b110 0
b0 !
b110 /
b100000 3
b100000 4
1#
#524000
0#
#526000
b100 '
b111 !
b1101 "
b1101 .
b1101 0
b100111 3
b100111 4
b1101 /
1#
#528000
0#
#530000
b101 '
b1010 "
b1010 .
b1010 0
b100 !
b1010 /
b100100 3
b100100 4
1#
#532000
0#
#534000
b110 '
b1100 !
b101 "
b101 .
b101 0
b101100 3
b101100 4
b101 /
1#
#536000
0#
#538000
b111 '
b1011 "
b1011 .
b1011 0
b11 !
b1011 /
b110011 3
b110011 4
1#
#540000
0#
#542000
b1000 '
b1010 !
b111 "
b111 .
b111 0
b1010 3
b1010 4
b111 /
1#
#544000
0#
#546000
b1001 '
b1111 "
b1111 .
b1111 0
b1111 /
b11010 3
b11010 4
1#
#548000
0#
#550000
b1010 '
b1011 !
b1110 "
b1110 .
b1110 0
b111011 3
b111011 4
b1110 /
1#
#552000
0#
#554000
b1011 '
b1100 "
b1100 .
b1100 0
b0 !
b1100 /
b10000 3
b10000 4
1#
#556000
0#
#558000
b1100 '
b11 !
b1000 "
b1000 .
b1000 0
b100011 3
b100011 4
b1000 /
1#
#560000
0#
#562000
b1101 '
b1 "
b1 .
b1 0
b110 !
b1 /
b100110 3
b100110 4
1#
#564000
0#
#566000
b1110 '
b101 !
b10 "
b10 .
b10 0
b100101 3
b100101 4
b10 /
1#
#568000
0#
#570000
b1111 '
b100 "
b100 .
b100 0
b1111 !
b100 /
b101111 3
b101111 4
1#
#572000
0#
#574000
b1010 -
b1010 &
b0 '
b1101 )
b0 *
b0 %
b1101 !
b1001 "
b1001 .
b1001 0
b111101 3
b111101 4
b1001 /
1#
#576000
0#
#577000
1$
#578000
b1010 "
b1010 .
b1010 0
b1111 !
b1010 /
b111111 3
b111111 4
1#
#580000
b1 '
0#
b1 *
b1010 (
0$
#582000
b10 '
b1010 !
b101 "
b101 .
b101 0
b11010 3
b11010 4
b101 /
1#
#584000
0#
#586000
b11 '
b1011 "
b1011 .
b1011 0
b1110 !
b1011 /
b111110 3
b111110 4
1#
#588000
0#
#590000
b100 '
b0 !
b111 "
b111 .
b111 0
b10000 3
b10000 4
b111 /
1#
#592000
0#
#594000
b101 '
b1111 "
b1111 .
b1111 0
b1110 !
b1111 /
b101110 3
b101110 4
1#
#596000
0#
#598000
b110 '
b10 !
b1110 "
b1110 .
b1110 0
b110010 3
b110010 4
b1110 /
1#
#600000
0#
#602000
b111 '
b1100 "
b1100 .
b1100 0
b1100 /
b10 3
b10 4
1#
#604000
0#
#606000
b1000 '
b111 !
b1000 "
b1000 .
b1000 0
b111 3
b111 4
b1000 /
1#
#608000
0#
#610000
b1001 '
b1 "
b1 .
b1 0
b1111 !
b1 /
b1111 3
b1111 4
1#
#612000
0#
#614000
b1010 '
b110 !
b10 "
b10 .
b10 0
b10110 3
b10110 4
b10 /
1#
#616000
0#
#618000
b1011 '
b100 "
b100 .
b100 0
b1000 !
b100 /
b101000 3
b101000 4
1#
#620000
0#
#622000
b1100 '
b11 !
b1001 "
b1001 .
b1001 0
b110011 3
b110011 4
b1001 /
1#
#624000
0#
#626000
b1101 '
b11 "
b11 .
b11 0
b1110 !
b11 /
b1110 3
b1110 4
1#
#628000
0#
#630000
b1110 '
b0 !
b110 "
b110 .
b110 0
b10000 3
b10000 4
b110 /
1#
#632000
0#
#634000
b1111 '
b1101 "
b1101 .
b1101 0
b110 !
b1101 /
b100110 3
b100110 4
1#
#636000
0#
#638000
b1011 -
b1011 &
b0 '
b110 )
b0 *
b0 %
b1010 "
b1010 .
b1010 0
b1010 /
1#
#640000
0#
#641000
1$
#642000
b1011 "
b1011 .
b1011 0
b1111 !
b1011 /
b111111 3
b111111 4
1#
#644000
b1 '
0#
b1 *
b1011 (
0$
#646000
b10 '
b10 !
b111 "
b111 .
b111 0
b10010 3
b10010 4
b111 /
1#
#648000
0#
#650000
b11 '
b1111 "
b1111 .
b1111 0
b1010 !
b1111 /
b101010 3
b101010 4
1#
#652000
0#
#654000
b100 '
b1110 "
b1110 .
b1110 0
b111010 3
b111010 4
b1110 /
1#
#656000
0#
#658000
b101 '
b1100 "
b1100 .
b1100 0
b10 !
b1100 /
b10010 3
b10010 4
1#
#660000
0#
#662000
b110 '
b111 !
b1000 "
b1000 .
b1000 0
b100111 3
b100111 4
b1000 /
1#
#664000
0#
#666000
b111 '
b1 "
b1 .
b1 0
b1110 !
b1 /
b101110 3
b101110 4
1#
#668000
0#
#670000
b1000 '
b101 !
b10 "
b10 .
b10 0
b110101 3
b110101 4
b10 /
1#
#672000
0#
#674000
b1001 '
b100 "
b100 .
b100 0
b1111 !
b100 /
b1111 3
b1111 4
1#
#676000
0#
#678000
b1010 '
b1100 !
b1001 "
b1001 .
b1001 0
b11100 3
b11100 4
b1001 /
1#
#680000
0#
#682000
b1011 '
b11 "
b11 .
b11 0
b1 !
b11 /
b110001 3
b110001 4
1#
#684000
0#
#686000
b1100 '
b1111 !
b110 "
b110 .
b110 0
b1111 3
b1111 4
b110 /
1#
#688000
0#
#690000
b1101 '
b1101 "
b1101 .
b1101 0
b1000 !
b1101 /
b11000 3
b11000 4
1#
#692000
0#
#694000
b1110 '
b1011 !
b1010 "
b1010 .
b1010 0
b111011 3
b111011 4
b1010 /
1#
#696000
0#
#698000
b1111 '
b101 "
b101 .
b101 0
b10 !
b101 /
b10010 3
b10010 4
1#
#700000
0#
#702000
b1100 -
b1100 &
b0 '
b1110 )
b0 *
b0 %
b1110 !
b1011 "
b1011 .
b1011 0
b101110 3
b101110 4
b1011 /
1#
#704000
0#
#705000
1$
#706000
b1100 "
b1100 .
b1100 0
b1111 !
b1100 /
b111111 3
b111111 4
1#
#708000
b1 '
0#
b1 *
b1100 (
0$
#710000
b10 '
b1100 !
b1000 "
b1000 .
b1000 0
b11100 3
b11100 4
b1000 /
1#
#712000
0#
#714000
b11 '
b1 "
b1 .
b1 0
b1001 !
b1 /
b111001 3
b111001 4
1#
#716000
0#
#718000
b100 '
b1011 !
b10 "
b10 .
b10 0
b11011 3
b11011 4
b10 /
1#
#720000
0#
#722000
b101 '
b100 "
b100 .
b100 0
b10 !
b100 /
b110010 3
b110010 4
1#
#724000
0#
#726000
b110 '
b111 !
b1001 "
b1001 .
b1001 0
b111 3
b111 4
b1001 /
1#
#728000
0#
#730000
b111 '
b11 "
b11 .
b11 0
b11 /
1#
#732000
0#
#734000
b1000 '
b10 !
b110 "
b110 .
b110 0
b10 3
b10 4
b110 /
1#
#736000
0#
#738000
b1001 '
b1101 "
b1101 .
b1101 0
b1101 /
1#
#740000
0#
#742000
b1010 '
b1111 !
b1010 "
b1010 .
b1010 0
b1111 3
b1111 4
b1010 /
1#
#744000
0#
#746000
b1011 '
b101 "
b101 .
b101 0
b1011 !
b101 /
b11011 3
b11011 4
1#
#748000
0#
#750000
b1100 '
b1100 !
b1011 "
b1011 .
b1011 0
b111100 3
b111100 4
b1011 /
1#
#752000
0#
#754000
b1101 '
b111 "
b111 .
b111 0
b100 !
b111 /
b10100 3
b10100 4
1#
#756000
0#
#758000
b1110 '
b110 !
b1111 "
b1111 .
b1111 0
b100110 3
b100110 4
b1111 /
1#
#760000
0#
#762000
b1111 '
b1110 "
b1110 .
b1110 0
b10 !
b1110 /
b100010 3
b100010 4
1#
#764000
0#
#766000
b1101 -
b1101 &
b0 '
b10 )
b0 *
b0 %
b1100 "
b1100 .
b1100 0
b1100 /
1#
#768000
0#
#769000
1$
#770000
b1101 "
b1101 .
b1101 0
b1111 !
b1101 /
b111111 3
b111111 4
1#
#772000
b1 '
0#
b1 *
b1101 (
0$
#774000
b10 '
b100 !
b1010 "
b1010 .
b1010 0
b10100 3
b10100 4
b1010 /
1#
#776000
0#
#778000
b11 '
b101 "
b101 .
b101 0
b1101 !
b101 /
b101101 3
b101101 4
1#
#780000
0#
#782000
b100 '
b1 !
b1011 "
b1011 .
b1011 0
b110001 3
b110001 4
b1011 /
1#
#784000
0#
#786000
b101 '
b111 "
b111 .
b111 0
b1110 !
b111 /
b1110 3
b1110 4
1#
#788000
0#
#790000
b110 '
b10 !
b1111 "
b1111 .
b1111 0
b10010 3
b10010 4
b1111 /
1#
#792000
0#
#794000
b111 '
b1110 "
b1110 .
b1110 0
b1011 !
b1110 /
b101011 3
b101011 4
1#
#796000
0#
#798000
b1000 '
b0 !
b1100 "
b1100 .
b1100 0
b110000 3
b110000 4
b1100 /
1#
#800000
0#
#802000
b1001 '
b1000 "
b1000 .
b1000 0
b10 !
b1000 /
b10 3
b10 4
1#
#804000
0#
#806000
b1010 '
b101 !
b1 "
b1 .
b1 0
b101 3
b101 4
b1 /
1#
#808000
0#
#810000
b1011 '
b10 "
b10 .
b10 0
b10 !
b10 /
b10 3
b10 4
1#
#812000
0#
#814000
b1100 '
b0 !
b100 "
b100 .
b100 0
b0 3
b0 4
b100 /
1#
#816000
0#
#818000
b1101 '
b1001 "
b1001 .
b1001 0
b10 !
b1001 /
b10 3
b10 4
1#
#820000
0#
#822000
b1110 '
b1101 !
b11 "
b11 .
b11 0
b1101 3
b1101 4
b11 /
1#
#824000
0#
#826000
b1111 '
b110 "
b110 .
b110 0
b110 !
b110 /
b10110 3
b10110 4
1#
#828000
0#
#830000
b1110 -
b1110 &
b0 '
b1010 )
b0 *
b0 %
b1010 !
b1101 "
b1101 .
b1101 0
b101010 3
b101010 4
b1101 /
1#
#832000
0#
#833000
1$
#834000
b1110 "
b1110 .
b1110 0
b1111 !
b1110 /
b111111 3
b111111 4
1#
#836000
b1 '
0#
b1 *
b1110 (
0$
#838000
b10 '
b1000 !
b1100 "
b1100 .
b1100 0
b11000 3
b11000 4
b1100 /
1#
#840000
0#
#842000
b11 '
b1000 "
b1000 .
b1000 0
b11 !
b1000 /
b110011 3
b110011 4
1#
#844000
0#
#846000
b100 '
b110 !
b1 "
b1 .
b1 0
b110 3
b110 4
b1 /
1#
#848000
0#
#850000
b101 '
b10 "
b10 .
b10 0
b100 !
b10 /
b100 3
b100 4
1#
