Project2/misr.v
module misr(
    input clk,
    input rst,
    input scan_in,
    input[3:0] grant_o,
    output[NBIT-1:0] signature,
    output scan_out
);

    parameter NBIT = 6;
    parameter seed = 6'b111010;
    reg [NBIT-1:0] dff;

    assign signature = dff;

    always @ (posedge clk) begin
        if(rst) begin
            dff <= seed;
        end
        else begin
            dff[0] <= grant_o[3]          ^ dff[NBIT-1];
            dff[1] <= grant_o[2] ^ dff[0] ^ dff[NBIT-1];
            dff[2] <= grant_o[1] ^ dff[1] ^ dff[NBIT-1];
            dff[3] <= grant_o[0] ^ dff[2] ^ dff[NBIT-1];
            dff[4] <=              dff[3] ^ dff[NBIT-1];
            dff[5] <=              dff[4] ^ dff[NBIT-1];
        end
    end

endmodule

Project2/misr_test_tb.v
`timescale 1ns / 1ps

module misr_test_tb;
    integer start = 0;
    integer seed = 0;
    integer niter = 0;
    integer done = 0;
    wire [6:0] signature_out_w;
    reg reset;
    reg clock;

    misr uut(
        .clk(clock),
        .rst(reset),
        .grant_o(0),
        .signature(signature_out_w)
    );


    initial begin
        $dumpfile("misr_test.vcd");
        $dumpvars();
        clock = 0;
        reset = 0;
    end

    initial begin
        #1;
        reset = 1;
        #3
        reset = 0;
        seed = signature_out_w;
        $display("Initial seed: %d" , seed);
        start = 1;
        wait (done == 1)
        $display("End in %d iterations" ,niter);
        $display("Should be 2^6-1 = %d" ,2**6-1);
    end

    always @ (posedge clock) begin
        if(start) begin
            if(signature_out_w == seed && niter != 0) begin
                done = 1;
                start = 0;
            end
            else begin
                $display("MISR output: %d" ,signature_out_w);
                niter++;  
            end
        end
    end

    initial begin
        #10000 $finish;
    end

    always
        #2  clock =  ! clock;

endmodule

Project2/misr_test.vcd
$date
	Sun May 17 19:06:27 2020
$end
$version
	Icarus Verilog
$end
$timescale
	1ps
$end
$scope module misr_test_tb $end
$var wire 7 ! signature_out_w [6:0] $end
$var reg 1 " clock $end
$var reg 1 # reset $end
$var integer 32 $ done [31:0] $end
$var integer 32 % niter [31:0] $end
$var integer 32 & seed [31:0] $end
$var integer 32 ' start [31:0] $end
$scope module uut $end
$var wire 1 " clk $end
$var wire 4 ( grant_o [3:0] $end
$var wire 1 # rst $end
$var wire 6 ) signature [5:0] $end
$var reg 6 * dff [5:0] $end
$upscope $end
$upscope $end
$enddefinitions $end
#0
$dumpvars
bx *
bx )
b0 (
b0 '
b0 &
b0 %
b0 $
0#
0"
b0xxxxxx !
$end
#1000
1#
#2000
b111010 !
b111010 )
b111010 *
1"
#4000
0"
b1 '
b111010 &
0#
#6000
b1011 !
b1011 )
b1011 *
b1 %
1"
#8000
0"
#10000
b10110 !
b10110 )
b10110 *
b10 %
1"
#12000
0"
#14000
b101100 !
b101100 )
b101100 *
b11 %
1"
#16000
0"
#18000
b100111 !
b100111 )
b100111 *
b100 %
1"
#20000
0"
#22000
b110001 !
b110001 )
b110001 *
b101 %
1"
#24000
0"
#26000
b11101 !
b11101 )
b11101 *
b110 %
1"
#28000
0"
#30000
b111010 !
b111010 )
b111010 *
b111 %
1"
#32000
0"
#34000
b1011 !
b1011 )
b1011 *
b0 '
b1 $
1"
#36000
0"
#38000
b10110 !
b10110 )
b10110 *
1"
#40000
0"
#42000
b101100 !
b101100 )
b101100 *
1"
#44000
0"
#46000
b100111 !
b100111 )
b100111 *
1"
#48000
0"
#50000
b110001 !
b110001 )
b110001 *
1"
#52000
0"
#54000
b11101 !
b11101 )
b11101 *
1"
#56000
0"
#58000
b111010 !
b111010 )
b111010 *
1"
#60000
0"
#62000
b1011 !
b1011 )
b1011 *
1"
#64000
0"
#66000
b10110 !
b10110 )
b10110 *
1"
#68000
0"
#70000
b101100 !
b101100 )
b101100 *
1"
#72000
0"
#74000
b100111 !
b100111 )
b100111 *
1"
#76000
0"
#78000
b110001 !
b110001 )
b110001 *
1"
#80000
0"
#82000
b11101 !
b11101 )
b11101 *
1"
#84000
0"
#86000
b111010 !
b111010 )
b111010 *
1"
#88000
0"
#90000
b1011 !
b1011 )
b1011 *
1"
#92000
0"
#94000
b10110 !
b10110 )
b10110 *
1"
#96000
0"
#98000
b101100 !
b101100 )
b101100 *
1"
#100000
0"
#102000
b100111 !
b100111 )
b100111 *
1"
#104000
0"
#106000
b110001 !
b110001 )
b110001 *
1"
#108000
0"
#110000
b11101 !
b11101 )
b11101 *
1"
#112000
0"
#114000
b111010 !
b111010 )
b111010 *
1"
#116000
0"
#118000
b1011 !
b1011 )
b1011 *
1"
#120000
0"
#122000
b10110 !
b10110 )
b10110 *
1"
#124000
0"
#126000
b101100 !
b101100 )
b101100 *
1"
#128000
0"
#130000
b100111 !
b100111 )
b100111 *
1"
#132000
0"
#134000
b110001 !
b110001 )
b110001 *
1"
#136000
0"
#138000
b11101 !
b11101 )
b11101 *
1"
#140000
0"
#142000
b111010 !
b111010 )
b111010 *
1"
#144000
0"
#146000
b1011 !
b1011 )
b1011 *
1"
#148000
0"
#150000
b10110 !
b10110 )
b10110 *
1"
#152000
0"
#154000
b101100 !
b101100 )
b101100 *
1"
#156000
0"
#158000
b100111 !
b100111 )
b100111 *
1"
#160000
0"
#162000
b110001 !
b110001 )
b110001 *
1"
#164000
0"
#166000
b11101 !
b11101 )
b11101 *
1"
#168000
0"
#170000
b111010 !
b111010 )
b111010 *
1"
#172000
0"
#174000
b1011 !
b1011 )
b1011 *
1"
#176000
0"
#178000
b10110 !
b10110 )
b10110 *
1"
#180000
0"
#182000
b101100 !
b101100 )
b101100 *
1"
#184000
0"
#186000
b100111 !
b100111 )
b100111 *
1"
#188000
0"
#190000
b110001 !
b110001 )
b110001 *
1"
#192000
0"
#194000
b11101 !
b11101 )
b11101 *
1"
#196000
0"
#198000
b111010 !
b111010 )
b111010 *
1"
#200000
0"
#202000
b1011 !
b1011 )
b1011 *
1"
#204000
0"
#206000
b10110 !
b10110 )
b10110 *
1"
#208000
0"
#210000
b101100 !
b101100 )
b101100 *
1"
#212000
0"
#214000
b100111 !
b100111 )
b100111 *
1"
#216000
0"
#218000
b110001 !
b110001 )
b110001 *
1"
#220000
0"
#222000
b11101 !
b11101 )
b11101 *
1"
#224000
0"
#226000
b111010 !
b111010 )
b111010 *
1"
#228000
0"
#230000
b1011 !
b1011 )
b1011 *
1"
#232000
0"
#234000
b10110 !
b10110 )
b10110 *
1"
#236000
0"
#238000
b101100 !
b101100 )
b101100 *
1"
#240000
0"
#242000
b100111 !
b100111 )
b100111 *
1"
#244000
0"
#246000
b110001 !
b110001 )
b110001 *
1"
#248000
0"
#250000
b11101 !
b11101 )
b11101 *
1"
#252000
0"
#254000
b111010 !
b111010 )
b111010 *
1"
#256000
0"
#258000
b1011 !
b1011 )
b1011 *
1"
#260000
0"
#262000
b10110 !
b10110 )
b10110 *
1"
#264000
0"
#266000
b101100 !
b101100 )
b101100 *
1"
#268000
0"
#270000
b100111 !
b100111 )
b100111 *
1"
#272000
0"
#274000
b110001 !
b110001 )
b110001 *
1"
#276000
0"
#278000
b11101 !
b11101 )
b11101 *
1"
#280000
0"
#282000
b111010 !
b111010 )
b111010 *
1"
#284000
0"
#286000
b1011 !
b1011 )
b1011 *
1"
#288000
0"
#290000
b10110 !
b10110 )
b10110 *
1"
#292000
0"
#294000
b101100 !
b101100 )
b101100 *
1"
#296000
0"
#298000
b100111 !
b100111 )
b100111 *
1"
#300000
0"
#302000
b110001 !
b110001 )
b110001 *
1"
#304000
0"
#306000
b11101 !
b11101 )
b11101 *
1"
#308000
0"
#310000
b111010 !
b111010 )
b111010 *
1"
#312000
0"
#314000
b1011 !
b1011 )
b1011 *
1"
#316000
0"
#318000
b10110 !
b10110 )
b10110 *
1"
#320000
0"
#322000
b101100 !
b101100 )
b101100 *
1"
#324000
0"
#326000
b100111 !
b100111 )
b100111 *
1"
#328000
0"
#330000
b110001 !
b110001 )
b110001 *
1"
#332000
0"
#334000
b11101 !
b11101 )
b11101 *
1"
#336000
0"
#338000
b111010 !
b111010 )
b111010 *
1"
#340000
0"
#342000
b1011 !
b1011 )
b1011 *
1"
#344000
0"
#346000
b10110 !
b10110 )
b10110 *
1"
#348000
0"
#350000
b101100 !
b101100 )
b101100 *
1"
#352000
0"
#354000
b100111 !
b100111 )
b100111 *
1"
#356000
0"
#358000
b110001 !
b110001 )
b110001 *
1"
#360000
0"
#362000
b11101 !
b11101 )
b11101 *
1"
#364000
0"
#366000
b111010 !
b111010 )
b111010 *
1"
#368000
0"
#370000
b1011 !
b1011 )
b1011 *
1"
#372000
0"
#374000
b10110 !
b10110 )
b10110 *
1"
#376000
0"
#378000
b101100 !
b101100 )
b101100 *
1"
#380000
0"
#382000
b100111 !
b100111 )
b100111 *
1"
#384000
0"
#386000
b110001 !
b110001 )
b110001 *
1"
#388000
0"
#390000
b11101 !
b11101 )
b11101 *
1"
#392000
0"
#394000
b111010 !
b111010 )
b111010 *
1"
#396000
0"
#398000
b1011 !
b1011 )
b1011 *
1"
#400000
0"
#402000
b10110 !
b10110 )
b10110 *
1"
#404000
0"
#406000
b101100 !
b101100 )
b101100 *
1"
#408000
0"
#410000
b100111 !
b100111 )
b100111 *
1"
#412000
0"
#414000
b110001 !
b110001 )
b110001 *
1"
#416000
0"
#418000
b11101 !
b11101 )
b11101 *
1"
#420000
0"
#422000
b111010 !
b111010 )
b111010 *
1"
#424000
0"
#426000
b1011 !
b1011 )
b1011 *
1"
#428000
0"
#430000
b10110 !
b10110 )
b10110 *
1"
#432000
0"
#434000
b101100 !
b101100 )
b101100 *
1"
#436000
0"
#438000
b100111 !
b100111 )
b100111 *
1"
#440000
0"
#442000
b110001 !
b110001 )
b110001 *
1"
#444000
0"
#446000
b11101 !
b11101 )
b11101 *
1"
#448000
0"
#450000
b111010 !
b111010 )
b111010 *
1"
#452000
0"
#454000
b1011 !
b1011 )
b1011 *
1"
#456000
0"
#458000
b10110 !
b10110 )
b10110 *
1"
#460000
0"
#462000
b101100 !
b101100 )
b101100 *
1"
#464000
0"
#466000
b100111 !
b100111 )
b100111 *
1"
#468000
0"
#470000
b110001 !
b110001 )
b110001 *
1"
#472000
0"
#474000
b11101 !
b11101 )
b11101 *
1"
#476000
0"
#478000
b111010 !
b111010 )
b111010 *
1"
#480000
0"
#482000
b1011 !
b1011 )
b1011 *
1"
#484000
0"
#486000
b10110 !
b10110 )
b10110 *
1"
#488000
0"
#490000
b101100 !
b101100 )
b101100 *
1"
#492000
0"
#494000
b100111 !
b100111 )
b100111 *
1"
#496000
0"
#498000
b110001 !
b110001 )
b110001 *
1"
#500000
0"
#502000
b11101 !
b11101 )
b11101 *
1"
#504000
0"
#506000
b111010 !
b111010 )
b111010 *
1"
#508000
0"
#510000
b1011 !
b1011 )
b1011 *
1"
#512000
0"
#514000
b10110 !
b10110 )
b10110 *
1"
#516000
0"
#518000
b101100 !
b101100 )
b101100 *
1"
#520000
0"
#522000
b100111 !
b100111 )
b100111 *
1"
#524000
0"
#526000
b110001 !
b110001 )
b110001 *
1"
#528000
0"
#530000
b11101 !
b11101 )
b11101 *
1"
#532000
0"
#534000
b111010 !
b111010 )
b111010 *
1"
#536000
0"
#538000
b1011 !
b1011 )
b1011 *
1"
#540000
0"
#542000
b10110 !
b10110 )
b10110 *
1"
#544000
0"
#546000
b101100 !
b101100 )
b101100 *
1"
#548000
0"
#550000
b100111 !
b100111 )
b100111 *
1"
#552000
0"
#554000
b110001 !
b110001 )
b110001 *
1"
#556000
0"
#558000
b11101 !
b11101 )
b11101 *
1"
#560000
0"
#562000
b111010 !
b111010 )
b111010 *
1"
#564000
0"
#566000
b1011 !
b1011 )
b1011 *
1"
#568000
0"
#570000
b10110 !
b10110 )
b10110 *
1"
#572000
0"
#574000
b101100 !
b101100 )
b101100 *
1"
#576000
0"
#578000
b100111 !
b100111 )
b100111 *
1"
#580000
0"
#582000
b110001 !
b110001 )
b110001 *
1"
#584000
0"
#586000
b11101 !
b11101 )
b11101 *
1"
#588000
0"
#590000
b111010 !
b111010 )
b111010 *
1"
#592000
0"
#594000
b1011 !
b1011 )
b1011 *
1"
#596000
0"
#598000
b10110 !
b10110 )
b10110 *
1"
#600000
0"
#602000
b101100 !
b101100 )
b101100 *
1"
#604000
0"
#606000
b100111 !
b100111 )
b100111 *
1"
#608000
0"
#610000
b110001 !
b110001 )
b110001 *
1"
#612000
0"
#614000
b11101 !
b11101 )
b11101 *
1"
#616000
0"
#618000
b111010 !
b111010 )
b111010 *
1"
#620000
0"
#622000
b1011 !
b1011 )
b1011 *
1"
#624000
0"
#626000
b10110 !
b10110 )
b10110 *
1"
#628000
0"
#630000
b101100 !
b101100 )
b101100 *
1"
#632000
0"
#634000
b100111 !
b100111 )
b100111 *
1"
#636000
0"
#638000
b110001 !
b110001 )
b110001 *
1"
#640000
0"
#642000
b11101 !
b11101 )
b11101 *
1"
#644000
0"
#646000
b111010 !
b111010 )
b111010 *
1"
#648000
0"
#650000
b1011 !
b1011 )
b1011 *
1"
#652000
0"
#654000
b10110 !
b10110 )
b10110 *
1"
#656000
0"
#658000
b101100 !
b101100 )
b101100 *
1"
#660000
0"
#662000
b100111 !
b100111 )
b100111 *
1"
#664000
0"
#666000
b110001 !
b110001 )
b110001 *
1"
#668000
0"
#670000
b11101 !
b11101 )
b11101 *
1"
#672000
0"
#674000
b111010 !
b111010 )
b111010 *
1"
#676000
0"
#678000
b1011 !
b1011 )
b1011 *
1"
#680000
0"
#682000
b10110 !
b10110 )
b10110 *
1"
#684000
0"
#686000
b101100 !
b101100 )
b101100 *
1"
#688000
0"
#690000
b100111 !
b100111 )
b100111 *
1"
#692000
0"
#694000
b110001 !
b110001 )
b110001 *
1"
#696000
0"
#698000
b11101 !
b11101 )
b11101 *
1"
#700000
0"
#702000
b111010 !
b111010 )
b111010 *
1"
#704000
0"
#706000
b1011 !
b1011 )
b1011 *
1"
#708000
0"
#710000
b10110 !
b10110 )
b10110 *
1"
#712000
0"
#714000
b101100 !
b101100 )
b101100 *
1"
#716000
0"
#718000
b100111 !
b100111 )
b100111 *
1"
#720000
0"
#722000
b110001 !
b110001 )
b110001 *
1"
#724000
0"
#726000
b11101 !
b11101 )
b11101 *
1"
#728000
0"
#730000
b111010 !
b111010 )
b111010 *
1"
#732000
0"
#734000
b1011 !
b1011 )
b1011 *
1"
#736000
0"
#738000
b10110 !
b10110 )
b10110 *
1"
#740000
0"
#742000
b101100 !
b101100 )
b101100 *
1"
#744000
0"
#746000
b100111 !
b100111 )
b100111 *
1"
#748000
0"
#750000
b110001 !
b110001 )
b110001 *
1"
#752000
0"
#754000
b11101 !
b11101 )
b11101 *
1"
#756000
0"
#758000
b111010 !
b111010 )
b111010 *
1"
#760000
0"
#762000
b1011 !
b1011 )
b1011 *
1"
#764000
0"
#766000
b10110 !
b10110 )
b10110 *
1"
#768000
0"
#770000
b101100 !
b101100 )
b101100 *
1"
#772000
0"
#774000
b100111 !
b100111 )
b100111 *
1"
#776000
0"
#778000
b110001 !
b110001 )
b110001 *
1"
#780000
0"
#782000
b11101 !
b11101 )
b11101 *
1"
#784000
0"
#786000
b111010 !
b111010 )
b111010 *
1"
#788000
0"
#790000
b1011 !
b1011 )
b1011 *
1"
#792000
0"
#794000
b10110 !
b10110 )
b10110 *
1"
#796000
0"
#798000
b101100 !
b101100 )
b101100 *
1"
#800000
0"
#802000
b100111 !
b100111 )
b100111 *
1"
#804000
0"
#806000
b110001 !
b110001 )
b110001 *
1"
#808000
0"
#810000
b11101 !
b11101 )
b11101 *
1"
#812000
0"
#814000
b111010 !
b111010 )
b111010 *
1"
#816000
0"
#818000
b1011 !
b1011 )
b1011 *
1"
#820000
0"
#822000
b10110 !
b10110 )
b10110 *
1"
#824000
0"
#826000
b101100 !
b101100 )
b101100 *
1"
#828000
0"
#830000
b100111 !
b100111 )
b100111 *
1"
#832000
0"
#834000
b110001 !
b110001 )
b110001 *
1"
#836000
0"
#838000
b11101 !
b11101 )
b11101 *
1"
#840000
0"
#842000
b111010 !
b111010 )
b111010 *
1"
#844000
0"
#846000
b1011 !
b1011 )
b1011 *
1"
#848000
0"
#850000
b10110 !
b10110 )
b10110 *
1"
#852000
0"
#854000
b101100 !
b101100 )
b101100 *
1"
#856000
0"
#858000
b100111 !
b100111 )
b100111 *
1"
#860000
0"
#862000
b110001 !
b110001 )
b110001 *
1"
#864000
0"
#866000
b11101 !
b11101 )
b11101 *
1"
#868000
0"
#870000
b111010 !
b111010 )
b111010 *
1"
#872000
0"
#874000
b1011 !
b1011 )
b1011 *
1"
#876000
0"
#878000
b10110 !
b10110 )
b10110 *
1"
#880000
0"
#882000
b101100 !
b101100 )
b101100 *
1"
#884000
0"
#886000
b100111 !
b100111 )
b100111 *
1"
#888000
0"
#890000
b110001 !
b110001 )
b110001 *
1"
#892000
0"
#894000
b11101 !
b11101 )
b11101 *
1"
#896000
0"
#898000
b111010 !
b111010 )
b111010 *
1"
#900000
0"
#902000
b1011 !
b1011 )
b1011 *
1"
#904000
0"
#906000
b10110 !
b10110 )
b10110 *
1"
#908000
0"
#910000
b101100 !
b101100 )
b101100 *
1"
#912000
0"
#914000
b100111 !
b100111 )
b100111 *
1"
#916000
0"
#918000
b110001 !
b110001 )
b110001 *
1"
#920000
0"
#922000
b11101 !
b11101 )
b11101 *
1"
#924000
0"
#926000
b111010 !
b111010 )
b111010 *
1"
#928000
0"
#930000
b1011 !
b1011 )
b1011 *
1"
#932000
0"
#934000
b10110 !
b10110 )
b10110 *
1"
#936000
0"
#938000
b101100 !
b101100 )
b101100 *
1"
#940000
0"
#942000
b100111 !
b100111 )
b100111 *
1"
#944000
0"
#946000
b110001 !
b110001 )
b110001 *
1"
#948000
0"
#950000
b11101 !
b11101 )
b11101 *
1"
#952000
0"
#954000
b111010 !
b111010 )
b111010 *
1"
#956000
0"
#958000
b1011 !
b1011 )
b1011 *
1"
#960000
0"
#962000
b10110 !
b10110 )
b10110 *
1"
#964000
0"
#966000
b101100 !
b101100 )
b101100 *
1"
#968000
0"
#970000
b100111 !
b100111 )
b100111 *
1"
#972000
0"
#974000
b110001 !
b110001 )
b110001 *
1"
#976000
0"
#978000
b11101 !
b11101 )
b11101 *
1"
#980000
0"
#982000
b111010 !
b111010 )
b111010 *
1"
#984000
0"
#986000
b1011 !
b1011 )
b1011 *
1"
#988000
0"
#990000
b10110 !
b10110 )
b10110 *
1"
#992000
0"
#994000
b101100 !
b101100 )
b101100 *
1"
#996000
0"
#998000
b100111 !
b100111 )
b100111 *
1"
#1000000
0"
#1002000
b110001 !
b110001 )
b110001 *
1"
#1004000
0"
#1006000
b11101 !
b11101 )
b11101 *
1"
#1008000
0"
#1010000
b111010 !
b111010 )
b111010 *
1"
#1012000
0"
#1014000
b1011 !
b1011 )
b1011 *
1"
#1016000
0"
#1018000
b10110 !
b10110 )
b10110 *
1"
#1020000
0"
#1022000
b101100 !
b101100 )
b101100 *
1"
#1024000
0"
#1026000
b100111 !
b100111 )
b100111 *
1"
#1028000
0"
#1030000
b110001 !
b110001 )
b110001 *
1"
#1032000
0"
#1034000
b11101 !
b11101 )
b11101 *
1"
#1036000
0"
#1038000
b111010 !
b111010 )
b111010 *
1"
#1040000
0"
#1042000
b1011 !
b1011 )
b1011 *
1"
#1044000
0"
#1046000
b10110 !
b10110 )
b10110 *
1"
#1048000
0"
#1050000
b101100 !
b101100 )
b101100 *
1"
#1052000
0"
#1054000
b100111 !
b100111 )
b100111 *
1"
#1056000
0"
#1058000
b110001 !
b110001 )
b110001 *
1"
#1060000
0"
#1062000
b11101 !
b11101 )
b11101 *
1"
#1064000
0"
#1066000
b111010 !
b111010 )
b111010 *
1"
#1068000
0"
#1070000
b1011 !
b1011 )
b1011 *
1"
#1072000
0"
#1074000
b10110 !
b10110 )
b10110 *
1"
#1076000
0"
#1078000
b101100 !
b101100 )
b101100 *
1"
#1080000
0"
#1082000
b100111 !
b100111 )
b100111 *
1"
#1084000
0"
#1086000
b110001 !
b110001 )
b110001 *
1"
#1088000
0"
#1090000
b11101 !
b11101 )
b11101 *
1"
#1092000
0"
#1094000
b111010 !
b111010 )
b111010 *
1"
#1096000
0"
#1098000
b1011 !
b1011 )
b1011 *
1"
#1100000
0"
#1102000
b10110 !
b10110 )
b10110 *
1"
#1104000
0"
#1106000
b101100 !
b101100 )
b101100 *
1"
#1108000
0"
#1110000
b100111 !
b100111 )
b100111 *
1"
#1112000
0"
#1114000
b110001 !
b110001 )
b110001 *
1"
#1116000
0"
#1118000
b11101 !
b11101 )
b11101 *
1"
#1120000
0"
#1122000
b111010 !
b111010 )
b111010 *
1"
#1124000
0"
#1126000
b1011 !
b1011 )
b1011 *
1"
#1128000
0"
#1130000
b10110 !
b10110 )
b10110 *
1"
#1132000
0"
#1134000
b101100 !
b101100 )
b101100 *
1"
#1136000
0"
#1138000
b100111 !
b100111 )
b100111 *
1"
#1140000
0"
#1142000
b110001 !
b110001 )
b110001 *
1"
#1144000
0"
#1146000
b11101 !
b11101 )
b11101 *
1"
#1148000
0"
#1150000
b111010 !
b111010 )
b111010 *
1"
#1152000
0"
#1154000
b1011 !
b1011 )
b1011 *
1"
#1156000
0"
#1158000
b10110 !
b10110 )
b10110 *
1"
#1160000
0"
#1162000
b101100 !
b101100 )
b101100 *
1"
#1164000
0"
#1166000
b100111 !
b100111 )
b100111 *
1"
#1168000
0"
#1170000
b110001 !
b110001 )
b110001 *
1"
#1172000
0"
#1174000
b11101 !
b11101 )
b11101 *
1"
#1176000
0"
#1178000
b111010 !
b111010 )
b111010 *
1"
#1180000
0"
#1182000
b1011 !
b1011 )
b1011 *
1"
#1184000
0"
#1186000
b10110 !
b10110 )
b10110 *
1"
#1188000
0"
#1190000
b101100 !
b101100 )
b101100 *
1"
#1192000
0"
#1194000
b100111 !
b100111 )
b100111 *
1"
#1196000
0"
#1198000
b110001 !
b110001 )
b110001 *
1"
#1200000
0"
#1202000
b11101 !
b11101 )
b11101 *
1"
#1204000
0"
#1206000
b111010 !
b111010 )
b111010 *
1"
#1208000
0"
#1210000
b1011 !
b1011 )
b1011 *
1"
#1212000
0"
#1214000
b10110 !
b10110 )
b10110 *
1"
#1216000
0"
#1218000
b101100 !
b101100 )
b101100 *
1"
#1220000
0"
#1222000
b100111 !
b100111 )
b100111 *
1"
#1224000
0"
#1226000
b110001 !
b110001 )
b110001 *
1"
#1228000
0"
#1230000
b11101 !
b11101 )
b11101 *
1"
#1232000
0"
#1234000
b111010 !
b111010 )
b111010 *
1"
#1236000
0"
#1238000
b1011 !
b1011 )
b1011 *
1"
#1240000
0"
#1242000
b10110 !
b10110 )
b10110 *
1"
#1244000
0"
#1246000
b101100 !
b101100 )
b101100 *
1"
#1248000
0"
#1250000
b100111 !
b100111 )
b100111 *
1"
#1252000
0"
#1254000
b110001 !
b110001 )
b110001 *
1"
#1256000
0"
#1258000
b11101 !
b11101 )
b11101 *
1"
#1260000
0"
#1262000
b111010 !
b111010 )
b111010 *
1"
#1264000
0"
#1266000
b1011 !
b1011 )
b1011 *
1"
#1268000
0"
#1270000
b10110 !
b10110 )
b10110 *
1"
#1272000
0"
#1274000
b101100 !
b101100 )
b101100 *
1"
#1276000
0"
#1278000
b100111 !
b100111 )
b100111 *
1"
#1280000
0"
#1282000
b110001 !
b110001 )
b110001 *
1"
#1284000
0"
#1286000
b11101 !
b11101 )
b11101 *
1"
#1288000
0"
#1290000
b111010 !
b111010 )
b111010 *
1"
#1292000
0"
#1294000
b1011 !
b1011 )
b1011 *
1"
#1296000
0"
#1298000
b10110 !
b10110 )
b10110 *
1"
#1300000
0"
#1302000
b101100 !
b101100 )
b101100 *
1"
#1304000
0"
#1306000
b100111 !
b100111 )
b100111 *
1"
#1308000
0"
#1310000
b110001 !
b110001 )
b110001 *
1"
#1312000
0"
#1314000
b11101 !
b11101 )
b11101 *
1"
#1316000
0"
#1318000
b111010 !
b111010 )
b111010 *
1"
#1320000
0"
#1322000
b1011 !
b1011 )
b1011 *
1"
#1324000
0"
#1326000
b10110 !
b10110 )
b10110 *
1"
#1328000
0"
#1330000
b101100 !
b101100 )
b101100 *
1"
#1332000
0"
#1334000
b100111 !
b100111 )
b100111 *
1"
#1336000
0"
#1338000
b110001 !
b110001 )
b110001 *
1"
#1340000
0"
#1342000
b11101 !
b11101 )
b11101 *
1"
#1344000
0"
#1346000
b111010 !
b111010 )
b111010 *
1"
#1348000
0"
#1350000
b1011 !
b1011 )
b1011 *
1"
#1352000
0"
#1354000
b10110 !
b10110 )
b10110 *
1"
#1356000
0"
#1358000
b101100 !
b101100 )
b101100 *
1"
#1360000
0"
#1362000
b100111 !
b100111 )
b100111 *
1"
#1364000
0"
#1366000
b110001 !
b110001 )
b110001 *
1"
#1368000
0"
#1370000
b11101 !
b11101 )
b11101 *
1"
#1372000
0"
#1374000
b111010 !
b111010 )
b111010 *
1"
#1376000
0"
#1378000
b1011 !
b1011 )
b1011 *
1"
#1380000
0"
#1382000
b10110 !
b10110 )
b10110 *
1"
#1384000
0"
#1386000
b101100 !
b101100 )
b101100 *
1"
#1388000
0"
#1390000
b100111 !
b100111 )
b100111 *
1"
#1392000
0"
#1394000
b110001 !
b110001 )
b110001 *
1"
#1396000
0"
#1398000
b11101 !
b11101 )
b11101 *
1"
#1400000
0"
#1402000
b111010 !
b111010 )
b111010 *
1"
#1404000
0"
#1406000
b1011 !
b1011 )
b1011 *
1"
#1408000
0"
#1410000
b10110 !
b10110 )
b10110 *
1"
#1412000
0"
#1414000
b101100 !
b101100 )
b101100 *
1"
#1416000
0"
#1418000
b100111 !
b100111 )
b100111 *
1"
#1420000
0"
#1422000
b110001 !
b110001 )
b110001 *
1"
#1424000
0"
#1426000
b11101 !
b11101 )
b11101 *
1"
#1428000
0"
#1430000
b111010 !
b111010 )
b111010 *
1"
#1432000
0"
#1434000
b1011 !
b1011 )
b1011 *
1"
#1436000
0"
#1438000
b10110 !
b10110 )
b10110 *
1"
#1440000
0"
#1442000
b101100 !
b101100 )
b101100 *
1"
#1444000
0"
#1446000
b100111 !
b100111 )
b100111 *
1"
#1448000
0"
#1450000
b110001 !
b110001 )
b110001 *
1"
#1452000
0"
#1454000
b11101 !
b11101 )
b11101 *
1"
#1456000
0"
#1458000
b111010 !
b111010 )
b111010 *
1"
#1460000
0"
#1462000
b1011 !
b1011 )
b1011 *
1"
#1464000
0"
#1466000
b10110 !
b10110 )
b10110 *
1"
#1468000
0"
#1470000
b101100 !
b101100 )
b101100 *
1"
#1472000
0"
#1474000
b100111 !
b100111 )
b100111 *
1"
#1476000
0"
#1478000
b110001 !
b110001 )
b110001 *
1"
#1480000
0"
#1482000
b11101 !
b11101 )
b11101 *
1"
#1484000
0"
#1486000
b111010 !
b111010 )
b111010 *
1"
#1488000
0"
#1490000
b1011 !
b1011 )
b1011 *
1"
#1492000
0"
#1494000
b10110 !
b10110 )
b10110 *
1"
#1496000
0"
#1498000
b101100 !
b101100 )
b101100 *
1"
#1500000
0"
#1502000
b100111 !
b100111 )
b100111 *
1"
#1504000
0"
#1506000
b110001 !
b110001 )
b110001 *
1"
#1508000
0"
#1510000
b11101 !
b11101 )
b11101 *
1"
#1512000
0"
#1514000
b111010 !
b111010 )
b111010 *
1"
#1516000
0"
#1518000
b1011 !
b1011 )
b1011 *
1"
#1520000
0"
#1522000
b10110 !
b10110 )
b10110 *
1"
#1524000
0"
#1526000
b101100 !
b101100 )
b101100 *
1"
#1528000
0"
#1530000
b100111 !
b100111 )
b100111 *
1"
#1532000
0"
#1534000
b110001 !
b110001 )
b110001 *
1"
#1536000
0"
#1538000
b11101 !
b11101 )
b11101 *
1"
#1540000
0"
#1542000
b111010 !
b111010 )
b111010 *
1"
#1544000
0"
#1546000
b1011 !
b1011 )
b1011 *
1"
#1548000
0"
#1550000
b10110 !
b10110 )
b10110 *
1"
#1552000
0"
#1554000
b101100 !
b101100 )
b101100 *
1"
#1556000
0"
#1558000
b100111 !
b100111 )
b100111 *
1"
#1560000
0"
#1562000
b110001 !
b110001 )
b110001 *
1"
#1564000
0"
#1566000
b11101 !
b11101 )
b11101 *
1"
#1568000
0"
#1570000
b111010 !
b111010 )
b111010 *
1"
#1572000
0"
#1574000
b1011 !
b1011 )
b1011 *
1"
#1576000
0"
#1578000
b10110 !
b10110 )
b10110 *
1"
#1580000
0"
#1582000
b101100 !
b101100 )
b101100 *
1"
#1584000
0"
#1586000
b100111 !
b100111 )
b100111 *
1"
#1588000
0"
#1590000
b110001 !
b110001 )
b110001 *
1"
#1592000
0"
#1594000
b11101 !
b11101 )
b11101 *
1"
#1596000
0"
#1598000
b111010 !
b111010 )
b111010 *
1"
#1600000
0"
#1602000
b1011 !
b1011 )
b1011 *
1"
#1604000
0"
#1606000
b10110 !
b10110 )
b10110 *
1"
#1608000
0"
#1610000
b101100 !
b101100 )
b101100 *
1"
#1612000
0"
#1614000
b100111 !
b100111 )
b100111 *
1"
#1616000
0"
#1618000
b110001 !
b110001 )
b110001 *
1"
#1620000
0"
#1622000
b11101 !
b11101 )
b11101 *
1"
#1624000
0"
#1626000
b111010 !
b111010 )
b111010 *
1"
#1628000
0"
#1630000
b1011 !
b1011 )
b1011 *
1"
#1632000
0"
#1634000
b10110 !
b10110 )
b10110 *
1"
#1636000
0"
#1638000
b101100 !
b101100 )
b101100 *
1"
#1640000
0"
#1642000
b100111 !
b100111 )
b100111 *
1"
#1644000
0"
#1646000
b110001 !
b110001 )
b110001 *
1"
#1648000
0"
#1650000
b11101 !
b11101 )
b11101 *
1"
#1652000
0"
#1654000
b111010 !
b111010 )
b111010 *
1"
#1656000
0"
#1658000
b1011 !
b1011 )
b1011 *
1"
#1660000
0"
#1662000
b10110 !
b10110 )
b10110 *
1"
#1664000
0"
#1666000
b101100 !
b101100 )
b101100 *
1"
#1668000
0"
