Project1/controller.v
`timescale 1ns / 1ps

module controller(
	input clk,
	input reset,
	input start,
	output init,
	output running,
	output toggle,
	output finish,
	output wire bist_end
);

reg [3:0] state, next_state; 
parameter IDLE=0, START=1, INIT=2, RUNNING=3, FINISH=4;
parameter NCLOCK = 10;

reg [$clog2(NCLOCK):0] ncounter;
reg complete;
reg toggle_r;
reg reset_latch;

always @ (posedge clk) begin
	if(reset) begin
		state       <= IDLE;
	end
	else if(start & (state == IDLE) & !reset_latch) begin
		state       <= START;
	end
	else
		state       <= next_state;
end


always @(*) begin
	case (state)
		START:
			next_state = INIT;
		INIT:
			next_state = RUNNING;
		RUNNING:
			if(ncounter == NCLOCK)
				next_state = FINISH;
		FINISH:
			next_state = IDLE;	
		default:
			next_state  = IDLE;
	endcase
end

assign init     = (state == INIT);
assign running  = (state == RUNNING) & (ncounter < NCLOCK+1);
assign finish   = (state == FINISH); 
assign bist_end = (complete) & !(reset | start) ;
assign toggle   = (state == RUNNING) & toggle_r;

always @ (posedge clk) begin
	if(reset | (state == FINISH)) begin
		toggle_r <= 0;
		ncounter <= 0;
	end	
	if(state == RUNNING) begin
		if(ncounter < NCLOCK) begin
			toggle_r <= !toggle_r;
		end
		else begin
			toggle_r <= 0;
		end
		ncounter <= ncounter + 1;
  	end
end

// always @ (negedge finish, posedge reset, posedge start) begin
// 	if(!finish & (state == END) & !reset)
// 		complete <= 1;
// end

always @ (negedge finish, posedge start, posedge reset) begin
	if(reset | start)
		complete = 0;
	else
		complete = 1;
	
end

always @ (posedge start) begin
	if(start & !(reset)) begin
		reset_latch <= 0;
	end
	else begin
		reset_latch <= 1;
	end

end

endmodule // controller

Project1/controller_tb.v

`timescale 1ns / 1ps

//===========SET TEST==========
`define normal
`define consequent_test
`define mid_start
`define start_reset
`define mid_reset

//==========SET NCLOCK========
`define reportval
//`define testval

module controller_tb;

    reg CLK;
    reg START;
    reg RESET;
    wire INIT, RUNNING, TOGGLE, FINISH, BIST_END;
    integer pulsecount = 0;
    integer runningcount = 0;

    parameter NCLOCK = 650; //650 for group 2

    controller uut(
        .clk(CLK),
        .reset(RESET),
        .start(START),
        .init(INIT),
        .running(RUNNING),
        .toggle(TOGGLE),
        .finish(FINISH),
        .bist_end(BIST_END)
    );                 
    
    initial
    begin
    	$dumpfile("dump.vcd");
        $dumpvars();
        
        CLK = 0;
    	START = 0;
    	RESET = 0;
    end

    always @ (posedge TOGGLE) begin
        pulsecount = pulsecount +1; 
    end

    always @ (posedge CLK) begin
        if(RUNNING)
            runningcount = runningcount + 1;
    end

    initial begin
        //first start

        `ifdef normal
        #13 RESET = 1;
        #13 RESET = 0;     
        #13 START = 1;
        #13 START = 0;
        `ifdef reportval
        #7000
        `endif
        `ifdef testval
        #125
        `endif
        $display("Number of pulses: %d pulses." ,pulsecount);
        $display("Time of running: %d clock pulses",runningcount-1); //-1 because the first rising edge of the clock doesent count
        pulsecount = 0;
        runningcount = 0;
        //======Normal test========
        `endif
        
        
        //first start
        `ifdef consequent_test
        #13 RESET = 1;
        #13 RESET = 0;     
        #13 START = 1;
        #13 START = 0;
        `ifdef reportval
        #7000
        `endif
        `ifdef testval
        #125
        `endif
        //second normal start
        #13 START = 1;
        #13 START = 0;
        #120
        //======consequent running proof========
        `endif
        

        `ifdef mid_start
        #13 RESET = 1;
        #13 RESET = 0;     
        #13 START = 1;
        #13 START = 0;
        #30
        //second normal start
        #13 START = 1;
        #13 START = 0;
        `ifdef reportval
        #7000
        `endif
        `ifdef testval
        #125
        `endif
        //======mid start proof========
        `endif

        `ifdef start_reset
        #13 RESET = 1;
        #13 RESET = 0;     
        #13 START = 1;
        #13 START = 0;
        #115
        #13 RESET = 1;
        #13 START = 1;
        #13 RESET = 0;
        #13 START = 0;
        #13 START = 1;
        #13 START = 0; 
        `ifdef reportval
        #7000
        `endif
        `ifdef testval
        #125
        `endif
        //======start and reset HIGH test========
        `endif

        `ifdef mid_reset
        #13 RESET = 1;
        #13 RESET = 0;     
        #13 START = 1;
        #13 START = 0;
        #50
        RESET = 1;
        #13
        RESET = 0;
        #13
        //second normal start
        #13 START = 1;
        #13 START = 0;
        `ifdef reportval
        #7000
        `endif
        `ifdef testval
        #125
        `endif
        //======mid start proof========
        `endif

    #100 $finish;

    end

    always
        #5  CLK =  ! CLK;


    


endmodule

Project1/waveform captures/midreset_test.vcd
$date
	Thu Apr  9 20:48:31 2020
$end
$version
	Icarus Verilog
$end
$timescale
	1ps
$end
$scope module controller_tb $end
$var wire 1 ! TOGGLE $end
$var wire 1 " RUNNING $end
$var wire 1 # INIT $end
$var wire 1 $ FINISH $end
$var wire 1 % BIST_END $end
$var reg 1 & CLK $end
$var reg 1 ' RESET $end
$var reg 1 ( START $end
$var integer 32 ) pulsecount [31:0] $end
$var integer 32 * runningcount [31:0] $end
$scope module uut $end
$var wire 1 % bist_end $end
$var wire 1 & clk $end
$var wire 1 ' reset $end
$var wire 1 " running $end
$var wire 1 ( start $end
$var wire 1 ! toggle $end
$var wire 1 # init $end
$var wire 1 $ finish $end
$var reg 1 + complete $end
$var reg 5 , ncounter [4:0] $end
$var reg 4 - next_state [3:0] $end
$var reg 1 . reset_latch $end
$var reg 4 / state [3:0] $end
$var reg 1 0 toggle_r $end
$upscope $end
$upscope $end
$enddefinitions $end
#0
$dumpvars
x0
bx /
x.
bx -
bx ,
x+
b0 *
b0 )
0(
0'
0&
x%
x$
x#
x"
x!
$end
#5000
1&
#10000
0&
#13000
0%
0+
1'
#15000
b0 -
0"
0!
b0 ,
00
0#
0$
b0 /
1&
#20000
0&
#25000
1&
#26000
0'
#30000
0&
#35000
1&
#39000
0.
1(
#40000
0&
#45000
b10 -
b1 /
1&
#50000
0&
#52000
0(
#55000
b11 -
1#
b10 /
1&
#60000
0&
#65000
1"
0#
b11 /
1&
#70000
0&
#75000
b1 )
1!
b1 ,
10
b1 *
1&
#80000
0&
#85000
0!
b10 ,
00
b10 *
1&
#90000
0&
#95000
b10 )
1!
b11 ,
10
b11 *
1&
#100000
0&
#102000
1'
#105000
0"
b0 -
0!
b0 /
b100 ,
00
b100 *
1&
#110000
0&
#115000
1&
0'
#120000
0&
#125000
1&
#130000
0&
#135000
1&
#140000
0&
#141000
1(
#145000
b10 -
b1 /
1&
#150000
0&
#154000
0(
#155000
b11 -
1#
b10 /
1&
#160000
0&
#165000
1"
0#
b11 /
1&
#170000
0&
#175000
b11 )
1!
b101 ,
10
b101 *
1&
#180000
0&
#185000
0!
b110 ,
00
b110 *
1&
#190000
0&
#195000
b100 )
1!
b111 ,
10
b111 *
1&
#200000
0&
#205000
0!
b1000 ,
00
b1000 *
1&
#210000
0&
#215000
b101 )
1!
b1001 ,
10
b1001 *
1&
#220000
0&
#225000
b100 -
0!
b1010 ,
00
b1010 *
1&
#230000
0&
#235000
b0 -
0"
b1011 ,
1$
b100 /
b1011 *
1&
#240000
0&
#245000
1%
1+
0$
b0 /
b0 ,
1&
